{
    "030200": [
        {
            "kode_prop": "030000",
            "propinsi": "Prov. Jawa Tengah",
            "kode_kab_kota": "030200",
            "kabupaten_kota": "Kab. Banyumas",
            "kode_kec": "030210",
            "kecamatan": "Kec. Kalibagor",
            "npsn": 69779211,
            "sekolah": "TK AISYIYAH BUSTANUL ATHFAL 1 KALIBAGOR",
            "bentuk": "Unknown",
            "status": "Swasta",
            "sinkron_terakhir": "14 Jan 2024 21:05:48",
            "sekolah_id_enkrip": "4938803988B52C1D8340"
        },
        {
            "kode_prop": "030000",
            "propinsi": "Prov. Jawa Tengah",
            "kode_kab_kota": "030200",
            "kabupaten_kota": "Kab. Banyumas",
            "kode_kec": "030210",
            "kecamatan": "Kec. Kalibagor",
            "npsn": 69779330,
            "sekolah": "TK AISYIYAH BUSTANUL ATHFAL 2 KALIBAGOR",
            "bentuk": "Unknown",
            "status": "Swasta",
            "sinkron_terakhir": "31 Jan 2024 11:52:26",
            "sekolah_id_enkrip": "ACD5BD34FFB6438403AC"
        },
        {
            "kode_prop": "030000",
            "propinsi": "Prov. Jawa Tengah",
            "kode_kab_kota": "030200",
            "kabupaten_kota": "Kab. Banyumas",
            "kode_kec": "030210",
            "kecamatan": "Kec. Kalibagor",
            "npsn": 69779233,
            "sekolah": "TK AL IRSYAD KALIORI",
            "bentuk": "Unknown",
            "status": "Swasta",
            "sinkron_terakhir": "29 Jan 2024 09:28:08",
            "sekolah_id_enkrip": "00FC5EF71DABF5EC4F41"
        },
        {
            "kode_prop": "030000",
            "propinsi": "Prov. Jawa Tengah",
            "kode_kab_kota": "030200",
            "kabupaten_kota": "Kab. Banyumas",
            "kode_kec": "030210",
            "kecamatan": "Kec. Kalibagor",
            "npsn": 70004369,
            "sekolah": "TK MUSLIMAT NU MASYITHOH 41",
            "bentuk": "Unknown",
            "status": "Swasta",
            "sinkron_terakhir": "29 Jan 2024 19:10:40",
            "sekolah_id_enkrip": "FCA12706E0F3B4CA645D"
        },
        {
            "kode_prop": "030000",
            "propinsi": "Prov. Jawa Tengah",
            "kode_kab_kota": "030200",
            "kabupaten_kota": "Kab. Banyumas",
            "kode_kec": "030210",
            "kecamatan": "Kec. Kalibagor",
            "npsn": 69873826,
            "sekolah": "TK MUTIARA BUNDA",
            "bentuk": "Unknown",
            "status": "Swasta",
            "sinkron_terakhir": "04 Dec 2023 10:42:34",
            "sekolah_id_enkrip": "90440CD96A9608F8DCE2"
        },
        {
            "kode_prop": "030000",
            "propinsi": "Prov. Jawa Tengah",
            "kode_kab_kota": "030200",
            "kabupaten_kota": "Kab. Banyumas",
            "kode_kec": "030210",
            "kecamatan": "Kec. Kalibagor",
            "npsn": 69779304,
            "sekolah": "TK PERTIWI 1 PAJERUKAN",
            "bentuk": "Unknown",
            "status": "Swasta",
            "sinkron_terakhir": "31 Jan 2024 08:21:53",
            "sekolah_id_enkrip": "537FB0F75DA8DF7708F7"
        },
        {
            "kode_prop": "030000",
            "propinsi": "Prov. Jawa Tengah",
            "kode_kab_kota": "030200",
            "kabupaten_kota": "Kab. Banyumas",
            "kode_kec": "030210",
            "kecamatan": "Kec. Kalibagor",
            "npsn": 69779375,
            "sekolah": "TK PERTIWI 2 PAJERUKAN",
            "bentuk": "Unknown",
            "status": "Swasta",
            "sinkron_terakhir": "22 Nov 2023 12:32:40",
            "sekolah_id_enkrip": "1B5E3D23C09C3EB7CC93"
        },
        {
            "kode_prop": "030000",
            "propinsi": "Prov. Jawa Tengah",
            "kode_kab_kota": "030200",
            "kabupaten_kota": "Kab. Banyumas",
            "kode_kec": "030210",
            "kecamatan": "Kec. Kalibagor",
            "npsn": 69779128,
            "sekolah": "TK PERTIWI KALIBAGOR",
            "bentuk": "Unknown",
            "status": "Swasta",
            "sinkron_terakhir": "05 Feb 2024 22:42:58",
            "sekolah_id_enkrip": "66F6D897CC0B726A033C"
        },
        {
            "kode_prop": "030000",
            "propinsi": "Prov. Jawa Tengah",
            "kode_kab_kota": "030200",
            "kabupaten_kota": "Kab. Banyumas",
            "kode_kec": "030210",
            "kecamatan": "Kec. Kalibagor",
            "npsn": 20355201,
            "sekolah": "TK PERTIWI KALICUPAK KIDUL",
            "bentuk": "Unknown",
            "status": "Swasta",
            "sinkron_terakhir": "12 Jan 2024 06:27:29",
            "sekolah_id_enkrip": "89F3AE359017B8329C5E"
        },
        {
            "kode_prop": "030000",
            "propinsi": "Prov. Jawa Tengah",
            "kode_kab_kota": "030200",
            "kabupaten_kota": "Kab. Banyumas",
            "kode_kec": "030210",
            "kecamatan": "Kec. Kalibagor",
            "npsn": 69779297,
            "sekolah": "TK PERTIWI KALICUPAK LOR",
            "bentuk": "Unknown",
            "status": "Swasta",
            "sinkron_terakhir": "29 Jan 2024 01:54:02",
            "sekolah_id_enkrip": "1A53CD04CA8B39B4F272"
        },
        {
            "kode_prop": "030000",
            "propinsi": "Prov. Jawa Tengah",
            "kode_kab_kota": "030200",
            "kabupaten_kota": "Kab. Banyumas",
            "kode_kec": "030210",
            "kecamatan": "Kec. Kalibagor",
            "npsn": 69779147,
            "sekolah": "TK PERTIWI KALIORI",
            "bentuk": "Unknown",
            "status": "Swasta",
            "sinkron_terakhir": "30 Jan 2024 17:52:57",
            "sekolah_id_enkrip": "74EEDE5D80BCA3F08E66"
        },
        {
            "kode_prop": "030000",
            "propinsi": "Prov. Jawa Tengah",
            "kode_kab_kota": "030200",
            "kabupaten_kota": "Kab. Banyumas",
            "kode_kec": "030210",
            "kecamatan": "Kec. Kalibagor",
            "npsn": 69779349,
            "sekolah": "TK PERTIWI KARANGDADAP",
            "bentuk": "Unknown",
            "status": "Swasta",
            "sinkron_terakhir": "04 Feb 2024 20:52:12",
            "sekolah_id_enkrip": "233B967E4BD70A9A8BA1"
        },
        {
            "kode_prop": "030000",
            "propinsi": "Prov. Jawa Tengah",
            "kode_kab_kota": "030200",
            "kabupaten_kota": "Kab. Banyumas",
            "kode_kec": "030210",
            "kecamatan": "Kec. Kalibagor",
            "npsn": 69779354,
            "sekolah": "TK PERTIWI PEKAJA",
            "bentuk": "Unknown",
            "status": "Swasta",
            "sinkron_terakhir": "28 Jan 2024 20:03:58",
            "sekolah_id_enkrip": "4E17C0731E42DF821269"
        },
        {
            "kode_prop": "030000",
            "propinsi": "Prov. Jawa Tengah",
            "kode_kab_kota": "030200",
            "kabupaten_kota": "Kab. Banyumas",
            "kode_kec": "030210",
            "kecamatan": "Kec. Kalibagor",
            "npsn": 69779258,
            "sekolah": "TK PERTIWI PETIR",
            "bentuk": "Unknown",
            "status": "Swasta",
            "sinkron_terakhir": "19 Jan 2024 10:30:25",
            "sekolah_id_enkrip": "D1E9B2D55C6D533C1DEA"
        },
        {
            "kode_prop": "030000",
            "propinsi": "Prov. Jawa Tengah",
            "kode_kab_kota": "030200",
            "kabupaten_kota": "Kab. Banyumas",
            "kode_kec": "030210",
            "kecamatan": "Kec. Kalibagor",
            "npsn": 69897135,
            "sekolah": "TK PERTIWI WLAHAR WETAN",
            "bentuk": "Unknown",
            "status": "Swasta",
            "sinkron_terakhir": "06 Feb 2024 17:56:21",
            "sekolah_id_enkrip": "46951800A9A81E0A4575"
        },
        {
            "kode_prop": "030000",
            "propinsi": "Prov. Jawa Tengah",
            "kode_kab_kota": "030200",
            "kabupaten_kota": "Kab. Banyumas",
            "kode_kec": "030210",
            "kecamatan": "Kec. Kalibagor",
            "npsn": 69779146,
            "sekolah": "TK VETERAN KALIBAGOR",
            "bentuk": "Unknown",
            "status": "Swasta",
            "sinkron_terakhir": "29 Jan 2024 21:22:57",
            "sekolah_id_enkrip": "FBB7980A1AFF32A95FDC"
        },
        {
            "kode_prop": "030000",
            "propinsi": "Prov. Jawa Tengah",
            "kode_kab_kota": "030200",
            "kabupaten_kota": "Kab. Banyumas",
            "kode_kec": "030210",
            "kecamatan": "Kec. Kalibagor",
            "npsn": 69779422,
            "sekolah": "KB AL AMANAH",
            "bentuk": "Unknown",
            "status": "Swasta",
            "sinkron_terakhir": "02 Feb 2024 12:04:46",
            "sekolah_id_enkrip": "FD5DFBA6584D2F3B15D1"
        },
        {
            "kode_prop": "030000",
            "propinsi": "Prov. Jawa Tengah",
            "kode_kab_kota": "030200",
            "kabupaten_kota": "Kab. Banyumas",
            "kode_kec": "030210",
            "kecamatan": "Kec. Kalibagor",
            "npsn": 69981433,
            "sekolah": "KB AMANAH UMMAH",
            "bentuk": "Unknown",
            "status": "Swasta",
            "sinkron_terakhir": "26 Jan 2024 12:44:54",
            "sekolah_id_enkrip": "E25F92DD96FCC531AF64"
        },
        {
            "kode_prop": "030000",
            "propinsi": "Prov. Jawa Tengah",
            "kode_kab_kota": "030200",
            "kabupaten_kota": "Kab. Banyumas",
            "kode_kec": "030210",
            "kecamatan": "Kec. Kalibagor",
            "npsn": 69779380,
            "sekolah": "KB ANAK CERIA",
            "bentuk": "Unknown",
            "status": "Swasta",
            "sinkron_terakhir": "12 Jan 2024 06:18:02",
            "sekolah_id_enkrip": "C0AEED879FF85C3BFA6C"
        },
        {
            "kode_prop": "030000",
            "propinsi": "Prov. Jawa Tengah",
            "kode_kab_kota": "030200",
            "kabupaten_kota": "Kab. Banyumas",
            "kode_kec": "030210",
            "kecamatan": "Kec. Kalibagor",
            "npsn": 69917174,
            "sekolah": "KB AROYYAN",
            "bentuk": "Unknown",
            "status": "Swasta",
            "sinkron_terakhir": "17 Jan 2024 05:00:00",
            "sekolah_id_enkrip": "EBB369785AED06197DF5"
        },
        {
            "kode_prop": "030000",
            "propinsi": "Prov. Jawa Tengah",
            "kode_kab_kota": "030200",
            "kabupaten_kota": "Kab. Banyumas",
            "kode_kec": "030210",
            "kecamatan": "Kec. Kalibagor",
            "npsn": 69779423,
            "sekolah": "KB CITRA LESTARI",
            "bentuk": "Unknown",
            "status": "Swasta",
            "sinkron_terakhir": "14 Jan 2024 20:44:14",
            "sekolah_id_enkrip": "398132600E330B6EA691"
        },
        {
            "kode_prop": "030000",
            "propinsi": "Prov. Jawa Tengah",
            "kode_kab_kota": "030200",
            "kabupaten_kota": "Kab. Banyumas",
            "kode_kec": "030210",
            "kecamatan": "Kec. Kalibagor",
            "npsn": 69910375,
            "sekolah": "KB DAR ALGHOD LILATFAL",
            "bentuk": "Unknown",
            "status": "Swasta",
            "sinkron_terakhir": "31 Dec 2023 18:02:23",
            "sekolah_id_enkrip": "95DC45B8D65EA8083FD3"
        },
        {
            "kode_prop": "030000",
            "propinsi": "Prov. Jawa Tengah",
            "kode_kab_kota": "030200",
            "kabupaten_kota": "Kab. Banyumas",
            "kode_kec": "030210",
            "kecamatan": "Kec. Kalibagor",
            "npsn": 69910389,
            "sekolah": "KB FATIHUL IHSAN",
            "bentuk": "Unknown",
            "status": "Swasta",
            "sinkron_terakhir": "25 Jan 2024 08:28:59",
            "sekolah_id_enkrip": "F1089BA9032EEE2BFB6C"
        },
        {
            "kode_prop": "030000",
            "propinsi": "Prov. Jawa Tengah",
            "kode_kab_kota": "030200",
            "kabupaten_kota": "Kab. Banyumas",
            "kode_kec": "030210",
            "kecamatan": "Kec. Kalibagor",
            "npsn": 69915260,
            "sekolah": "KB FATIMAH 4",
            "bentuk": "Unknown",
            "status": "Swasta",
            "sinkron_terakhir": "15 Jan 2024 15:28:51",
            "sekolah_id_enkrip": "62A536DCBC057993DC47"
        },
        {
            "kode_prop": "030000",
            "propinsi": "Prov. Jawa Tengah",
            "kode_kab_kota": "030200",
            "kabupaten_kota": "Kab. Banyumas",
            "kode_kec": "030210",
            "kecamatan": "Kec. Kalibagor",
            "npsn": 69911428,
            "sekolah": "KB HARAPAN BANGSA",
            "bentuk": "Unknown",
            "status": "Swasta",
            "sinkron_terakhir": "14 Jan 2024 20:16:01",
            "sekolah_id_enkrip": "2B348DA726E5141F5314"
        },
        {
            "kode_prop": "030000",
            "propinsi": "Prov. Jawa Tengah",
            "kode_kab_kota": "030200",
            "kabupaten_kota": "Kab. Banyumas",
            "kode_kec": "030210",
            "kecamatan": "Kec. Kalibagor",
            "npsn": 69779408,
            "sekolah": "KB MAKKAH",
            "bentuk": "Unknown",
            "status": "Swasta",
            "sinkron_terakhir": "29 Aug 2022 23:05:11",
            "sekolah_id_enkrip": "213BEC7CB419EBBE34B7"
        },
        {
            "kode_prop": "030000",
            "propinsi": "Prov. Jawa Tengah",
            "kode_kab_kota": "030200",
            "kabupaten_kota": "Kab. Banyumas",
            "kode_kec": "030210",
            "kecamatan": "Kec. Kalibagor",
            "npsn": 69911314,
            "sekolah": "KB PERMATA BELIA",
            "bentuk": "Unknown",
            "status": "Swasta",
            "sinkron_terakhir": "29 Dec 2023 21:04:00",
            "sekolah_id_enkrip": "8C7B8584FAFA56096BD3"
        },
        {
            "kode_prop": "030000",
            "propinsi": "Prov. Jawa Tengah",
            "kode_kab_kota": "030200",
            "kabupaten_kota": "Kab. Banyumas",
            "kode_kec": "030210",
            "kecamatan": "Kec. Kalibagor",
            "npsn": 69779394,
            "sekolah": "KB TUNAS MUDA",
            "bentuk": "Unknown",
            "status": "Swasta",
            "sinkron_terakhir": "14 Jan 2024 23:39:38",
            "sekolah_id_enkrip": "7905B40746297C22174B"
        },
        {
            "kode_prop": "030000",
            "propinsi": "Prov. Jawa Tengah",
            "kode_kab_kota": "030200",
            "kabupaten_kota": "Kab. Banyumas",
            "kode_kec": "030210",
            "kecamatan": "Kec. Kalibagor",
            "npsn": 69917515,
            "sekolah": "PAUD TPQ AL MUHAJIRIN",
            "bentuk": "Unknown",
            "status": "Swasta",
            "sinkron_terakhir": "29 Jan 2024 09:22:27",
            "sekolah_id_enkrip": "04A476B66F4A593346CF"
        },
        {
            "kode_prop": "030000",
            "propinsi": "Prov. Jawa Tengah",
            "kode_kab_kota": "030200",
            "kabupaten_kota": "Kab. Banyumas",
            "kode_kec": "030210",
            "kecamatan": "Kec. Kalibagor",
            "npsn": 69779470,
            "sekolah": "POS PAUD BANOWATI",
            "bentuk": "Unknown",
            "status": "Swasta",
            "sinkron_terakhir": "18 Jan 2024 05:20:37",
            "sekolah_id_enkrip": "1E33DE1D9F4C31CB1B8C"
        },
        {
            "kode_prop": "030000",
            "propinsi": "Prov. Jawa Tengah",
            "kode_kab_kota": "030200",
            "kabupaten_kota": "Kab. Banyumas",
            "kode_kec": "030210",
            "kecamatan": "Kec. Kalibagor",
            "npsn": 69779504,
            "sekolah": "POS PAUD BINA PALUPI",
            "bentuk": "Unknown",
            "status": "Swasta",
            "sinkron_terakhir": "22 Jan 2024 20:08:05",
            "sekolah_id_enkrip": "325EAD49E10AD4044201"
        },
        {
            "kode_prop": "030000",
            "propinsi": "Prov. Jawa Tengah",
            "kode_kab_kota": "030200",
            "kabupaten_kota": "Kab. Banyumas",
            "kode_kec": "030210",
            "kecamatan": "Kec. Kalibagor",
            "npsn": 69779541,
            "sekolah": "POS PAUD BOUGENVILLE",
            "bentuk": "Unknown",
            "status": "Swasta",
            "sinkron_terakhir": "15 Jan 2024 18:25:49",
            "sekolah_id_enkrip": "581D10CC905B7BA1D5E0"
        },
        {
            "kode_prop": "030000",
            "propinsi": "Prov. Jawa Tengah",
            "kode_kab_kota": "030200",
            "kabupaten_kota": "Kab. Banyumas",
            "kode_kec": "030210",
            "kecamatan": "Kec. Kalibagor",
            "npsn": 69779526,
            "sekolah": "POS PAUD DELIMA MEKAR",
            "bentuk": "Unknown",
            "status": "Swasta",
            "sinkron_terakhir": "15 Jan 2024 16:57:39",
            "sekolah_id_enkrip": "94615F07118A35FF302D"
        },
        {
            "kode_prop": "030000",
            "propinsi": "Prov. Jawa Tengah",
            "kode_kab_kota": "030200",
            "kabupaten_kota": "Kab. Banyumas",
            "kode_kec": "030210",
            "kecamatan": "Kec. Kalibagor",
            "npsn": 69779552,
            "sekolah": "POS PAUD KUNCUP MEKAR",
            "bentuk": "Unknown",
            "status": "Swasta",
            "sinkron_terakhir": "18 Jan 2024 16:24:36",
            "sekolah_id_enkrip": "12406C198D9B0BF22B44"
        },
        {
            "kode_prop": "030000",
            "propinsi": "Prov. Jawa Tengah",
            "kode_kab_kota": "030200",
            "kabupaten_kota": "Kab. Banyumas",
            "kode_kec": "030210",
            "kecamatan": "Kec. Kalibagor",
            "npsn": 69779507,
            "sekolah": "POS PAUD MEKAR SARI SROWOT",
            "bentuk": "Unknown",
            "status": "Swasta",
            "sinkron_terakhir": "17 Jan 2024 19:12:54",
            "sekolah_id_enkrip": "82CA7365A653C7A8F276"
        },
        {
            "kode_prop": "030000",
            "propinsi": "Prov. Jawa Tengah",
            "kode_kab_kota": "030200",
            "kabupaten_kota": "Kab. Banyumas",
            "kode_kec": "030210",
            "kecamatan": "Kec. Kalibagor",
            "npsn": 69911439,
            "sekolah": "POS PAUD MUGI RAHAYU",
            "bentuk": "Unknown",
            "status": "Swasta",
            "sinkron_terakhir": "31 Dec 2023 19:24:44",
            "sekolah_id_enkrip": "09B44DEBF9CD53D74542"
        },
        {
            "kode_prop": "030000",
            "propinsi": "Prov. Jawa Tengah",
            "kode_kab_kota": "030200",
            "kabupaten_kota": "Kab. Banyumas",
            "kode_kec": "030210",
            "kecamatan": "Kec. Kalibagor",
            "npsn": 69779508,
            "sekolah": "POS PAUD MULIA BANGSA",
            "bentuk": "Unknown",
            "status": "Swasta",
            "sinkron_terakhir": "17 Dec 2023 18:30:25",
            "sekolah_id_enkrip": "BDB5B8E5B1C38FD0E046"
        },
        {
            "kode_prop": "030000",
            "propinsi": "Prov. Jawa Tengah",
            "kode_kab_kota": "030200",
            "kabupaten_kota": "Kab. Banyumas",
            "kode_kec": "030210",
            "kecamatan": "Kec. Kalibagor",
            "npsn": 69779510,
            "sekolah": "POS PAUD PUSPITASARI KALIBAGOR",
            "bentuk": "Unknown",
            "status": "Swasta",
            "sinkron_terakhir": "29 Aug 2023 22:01:26",
            "sekolah_id_enkrip": "35FF96856A52035F5DD7"
        },
        {
            "kode_prop": "030000",
            "propinsi": "Prov. Jawa Tengah",
            "kode_kab_kota": "030200",
            "kabupaten_kota": "Kab. Banyumas",
            "kode_kec": "030210",
            "kecamatan": "Kec. Kalibagor",
            "npsn": 20302656,
            "sekolah": "SD N 2 PAJERUKAN",
            "bentuk": "Unknown",
            "status": "Negeri",
            "sinkron_terakhir": "05 Feb 2024 09:52:51",
            "sekolah_id_enkrip": "ACE7DF6F0B4F6844C218"
        },
        {
            "kode_prop": "030000",
            "propinsi": "Prov. Jawa Tengah",
            "kode_kab_kota": "030200",
            "kabupaten_kota": "Kab. Banyumas",
            "kode_kec": "030210",
            "kecamatan": "Kec. Kalibagor",
            "npsn": 20302078,
            "sekolah": "SD N KALISOGRA WETAN",
            "bentuk": "Unknown",
            "status": "Negeri",
            "sinkron_terakhir": "01 Feb 2024 13:26:13",
            "sekolah_id_enkrip": "21D3ECA652BE5A060EAD"
        },
        {
            "kode_prop": "030000",
            "propinsi": "Prov. Jawa Tengah",
            "kode_kab_kota": "030200",
            "kabupaten_kota": "Kab. Banyumas",
            "kode_kec": "030210",
            "kecamatan": "Kec. Kalibagor",
            "npsn": 20302294,
            "sekolah": "SD NEGERI 1 KALIORI",
            "bentuk": "Unknown",
            "status": "Negeri",
            "sinkron_terakhir": "06 Feb 2024 07:40:28",
            "sekolah_id_enkrip": "C96A0A95A030020AD269"
        },
        {
            "kode_prop": "030000",
            "propinsi": "Prov. Jawa Tengah",
            "kode_kab_kota": "030200",
            "kabupaten_kota": "Kab. Banyumas",
            "kode_kec": "030210",
            "kecamatan": "Kec. Kalibagor",
            "npsn": 20302711,
            "sekolah": "SD NEGERI 1 PAJERUKAN",
            "bentuk": "Unknown",
            "status": "Negeri",
            "sinkron_terakhir": "02 Feb 2024 10:29:20",
            "sekolah_id_enkrip": "7A7DEEC239B77E3C926E"
        },
        {
            "kode_prop": "030000",
            "propinsi": "Prov. Jawa Tengah",
            "kode_kab_kota": "030200",
            "kabupaten_kota": "Kab. Banyumas",
            "kode_kec": "030210",
            "kecamatan": "Kec. Kalibagor",
            "npsn": 20302730,
            "sekolah": "SD NEGERI 1 PEKAJA",
            "bentuk": "Unknown",
            "status": "Negeri",
            "sinkron_terakhir": "25 Jan 2024 04:37:02",
            "sekolah_id_enkrip": "F331730F8C14D82699CA"
        },
        {
            "kode_prop": "030000",
            "propinsi": "Prov. Jawa Tengah",
            "kode_kab_kota": "030200",
            "kabupaten_kota": "Kab. Banyumas",
            "kode_kec": "030210",
            "kecamatan": "Kec. Kalibagor",
            "npsn": 20302804,
            "sekolah": "SD NEGERI 1 SROWOT",
            "bentuk": "Unknown",
            "status": "Negeri",
            "sinkron_terakhir": "31 Jan 2024 10:36:30",
            "sekolah_id_enkrip": "ED222E0696241853D477"
        },
        {
            "kode_prop": "030000",
            "propinsi": "Prov. Jawa Tengah",
            "kode_kab_kota": "030200",
            "kabupaten_kota": "Kab. Banyumas",
            "kode_kec": "030210",
            "kecamatan": "Kec. Kalibagor",
            "npsn": 20302544,
            "sekolah": "SD NEGERI 2 KALIBAGOR",
            "bentuk": "Unknown",
            "status": "Negeri",
            "sinkron_terakhir": "30 Jan 2024 08:19:28",
            "sekolah_id_enkrip": "7B34EB27A3C0B2698BFF"
        },
        {
            "kode_prop": "030000",
            "propinsi": "Prov. Jawa Tengah",
            "kode_kab_kota": "030200",
            "kabupaten_kota": "Kab. Banyumas",
            "kode_kec": "030210",
            "kecamatan": "Kec. Kalibagor",
            "npsn": 20302557,
            "sekolah": "SD NEGERI 2 KALIORI",
            "bentuk": "Unknown",
            "status": "Negeri",
            "sinkron_terakhir": "25 Jan 2024 08:59:12",
            "sekolah_id_enkrip": "0291ECD5A85CBAC8AE18"
        },
        {
            "kode_prop": "030000",
            "propinsi": "Prov. Jawa Tengah",
            "kode_kab_kota": "030200",
            "kabupaten_kota": "Kab. Banyumas",
            "kode_kec": "030210",
            "kecamatan": "Kec. Kalibagor",
            "npsn": 20301736,
            "sekolah": "SD NEGERI 2 PEKAJA",
            "bentuk": "Unknown",
            "status": "Negeri",
            "sinkron_terakhir": "01 Feb 2024 21:40:38",
            "sekolah_id_enkrip": "060182F8E04D8D38C073"
        },
        {
            "kode_prop": "030000",
            "propinsi": "Prov. Jawa Tengah",
            "kode_kab_kota": "030200",
            "kabupaten_kota": "Kab. Banyumas",
            "kode_kec": "030210",
            "kecamatan": "Kec. Kalibagor",
            "npsn": 20301764,
            "sekolah": "SD NEGERI 3 KALIORI",
            "bentuk": "Unknown",
            "status": "Negeri",
            "sinkron_terakhir": "25 Jan 2024 14:06:32",
            "sekolah_id_enkrip": "348E920206224A0B0BEE"
        },
        {
            "kode_prop": "030000",
            "propinsi": "Prov. Jawa Tengah",
            "kode_kab_kota": "030200",
            "kabupaten_kota": "Kab. Banyumas",
            "kode_kec": "030210",
            "kecamatan": "Kec. Kalibagor",
            "npsn": 20301556,
            "sekolah": "SD NEGERI 3 PEKAJA",
            "bentuk": "Unknown",
            "status": "Negeri",
            "sinkron_terakhir": "25 Jan 2024 11:52:53",
            "sekolah_id_enkrip": "41930D06AC71440893A3"
        },
        {
            "kode_prop": "030000",
            "propinsi": "Prov. Jawa Tengah",
            "kode_kab_kota": "030200",
            "kabupaten_kota": "Kab. Banyumas",
            "kode_kec": "030210",
            "kecamatan": "Kec. Kalibagor",
            "npsn": 20302061,
            "sekolah": "SD NEGERI KALICUPAK KIDUL",
            "bentuk": "Unknown",
            "status": "Negeri",
            "sinkron_terakhir": "02 Feb 2024 08:42:05",
            "sekolah_id_enkrip": "B0025C76B08D43A46F83"
        },
        {
            "kode_prop": "030000",
            "propinsi": "Prov. Jawa Tengah",
            "kode_kab_kota": "030200",
            "kabupaten_kota": "Kab. Banyumas",
            "kode_kec": "030210",
            "kecamatan": "Kec. Kalibagor",
            "npsn": 20302062,
            "sekolah": "SD NEGERI KALICUPAK LOR",
            "bentuk": "Unknown",
            "status": "Negeri",
            "sinkron_terakhir": "01 Feb 2024 19:55:58",
            "sekolah_id_enkrip": "06B89D32DAE096F66C6A"
        },
        {
            "kode_prop": "030000",
            "propinsi": "Prov. Jawa Tengah",
            "kode_kab_kota": "030200",
            "kabupaten_kota": "Kab. Banyumas",
            "kode_kec": "030210",
            "kecamatan": "Kec. Kalibagor",
            "npsn": 20302799,
            "sekolah": "SD NEGERI SURO",
            "bentuk": "Unknown",
            "status": "Negeri",
            "sinkron_terakhir": "05 Feb 2024 09:37:27",
            "sekolah_id_enkrip": "2FE3A1973D5D5EAECFFF"
        },
        {
            "kode_prop": "030000",
            "propinsi": "Prov. Jawa Tengah",
            "kode_kab_kota": "030200",
            "kabupaten_kota": "Kab. Banyumas",
            "kode_kec": "030210",
            "kecamatan": "Kec. Kalibagor",
            "npsn": 20302150,
            "sekolah": "SD NEGERI WLAHAR WETAN",
            "bentuk": "Unknown",
            "status": "Negeri",
            "sinkron_terakhir": "18 Jan 2024 09:39:22",
            "sekolah_id_enkrip": "29A6C6FB634D26FA953A"
        },
        {
            "kode_prop": "030000",
            "propinsi": "Prov. Jawa Tengah",
            "kode_kab_kota": "030200",
            "kabupaten_kota": "Kab. Banyumas",
            "kode_kec": "030210",
            "kecamatan": "Kec. Kalibagor",
            "npsn": 20302292,
            "sekolah": "SDN 1 KALIBAGOR",
            "bentuk": "Unknown",
            "status": "Negeri",
            "sinkron_terakhir": "05 Feb 2024 14:09:36",
            "sekolah_id_enkrip": "26A1C9A0EA0ECF8561FE"
        },
        {
            "kode_prop": "030000",
            "propinsi": "Prov. Jawa Tengah",
            "kode_kab_kota": "030200",
            "kabupaten_kota": "Kab. Banyumas",
            "kode_kec": "030210",
            "kecamatan": "Kec. Kalibagor",
            "npsn": 20302831,
            "sekolah": "SDN 1 PETIR",
            "bentuk": "Unknown",
            "status": "Negeri",
            "sinkron_terakhir": "02 Feb 2024 09:53:27",
            "sekolah_id_enkrip": "047B03C093B3B32F7BE0"
        },
        {
            "kode_prop": "030000",
            "propinsi": "Prov. Jawa Tengah",
            "kode_kab_kota": "030200",
            "kabupaten_kota": "Kab. Banyumas",
            "kode_kec": "030210",
            "kecamatan": "Kec. Kalibagor",
            "npsn": 20301733,
            "sekolah": "SDN 2 PETIR",
            "bentuk": "Unknown",
            "status": "Negeri",
            "sinkron_terakhir": "22 Jan 2024 13:02:51",
            "sekolah_id_enkrip": "AE4B5F9D2CA10BEB5572"
        },
        {
            "kode_prop": "030000",
            "propinsi": "Prov. Jawa Tengah",
            "kode_kab_kota": "030200",
            "kabupaten_kota": "Kab. Banyumas",
            "kode_kec": "030210",
            "kecamatan": "Kec. Kalibagor",
            "npsn": 20301685,
            "sekolah": "SDN 2 SROWOT",
            "bentuk": "Unknown",
            "status": "Negeri",
            "sinkron_terakhir": "17 Jan 2024 09:07:47",
            "sekolah_id_enkrip": "E09F28EBA7D3ABDFDC0E"
        },
        {
            "kode_prop": "030000",
            "propinsi": "Prov. Jawa Tengah",
            "kode_kab_kota": "030200",
            "kabupaten_kota": "Kab. Banyumas",
            "kode_kec": "030210",
            "kecamatan": "Kec. Kalibagor",
            "npsn": 20301552,
            "sekolah": "SDN 4 KALIBAGOR",
            "bentuk": "Unknown",
            "status": "Negeri",
            "sinkron_terakhir": "05 Feb 2024 08:31:01",
            "sekolah_id_enkrip": "3529CBCD8BB4854B5E2B"
        },
        {
            "kode_prop": "030000",
            "propinsi": "Prov. Jawa Tengah",
            "kode_kab_kota": "030200",
            "kabupaten_kota": "Kab. Banyumas",
            "kode_kec": "030210",
            "kecamatan": "Kec. Kalibagor",
            "npsn": 20302096,
            "sekolah": "SDN KARANGDADAP",
            "bentuk": "Unknown",
            "status": "Negeri",
            "sinkron_terakhir": "30 Jan 2024 09:45:21",
            "sekolah_id_enkrip": "94BD68875044B3D8C4F9"
        },
        {
            "kode_prop": "030000",
            "propinsi": "Prov. Jawa Tengah",
            "kode_kab_kota": "030200",
            "kabupaten_kota": "Kab. Banyumas",
            "kode_kec": "030210",
            "kecamatan": "Kec. Kalibagor",
            "npsn": 69966291,
            "sekolah": "SD ALAM HAYUBA",
            "bentuk": "Unknown",
            "status": "Swasta",
            "sinkron_terakhir": "30 Jan 2024 18:54:42",
            "sekolah_id_enkrip": "CC2492FDE2543C2CC1A0"
        },
        {
            "kode_prop": "030000",
            "propinsi": "Prov. Jawa Tengah",
            "kode_kab_kota": "030200",
            "kabupaten_kota": "Kab. Banyumas",
            "kode_kec": "030210",
            "kecamatan": "Kec. Kalibagor",
            "npsn": 69967429,
            "sekolah": "SD IT NURUL UMMAH",
            "bentuk": "Unknown",
            "status": "Swasta",
            "sinkron_terakhir": "02 Feb 2024 10:14:08",
            "sekolah_id_enkrip": "62CF50DC626C365853DC"
        },
        {
            "kode_prop": "030000",
            "propinsi": "Prov. Jawa Tengah",
            "kode_kab_kota": "030200",
            "kabupaten_kota": "Kab. Banyumas",
            "kode_kec": "030210",
            "kecamatan": "Kec. Kalibagor",
            "npsn": 20301994,
            "sekolah": "SMP NEGERI 1 KALIBAGOR",
            "bentuk": "Unknown",
            "status": "Negeri",
            "sinkron_terakhir": "05 Feb 2024 11:50:05",
            "sekolah_id_enkrip": "4F6F0175959579C6FBB9"
        },
        {
            "kode_prop": "030000",
            "propinsi": "Prov. Jawa Tengah",
            "kode_kab_kota": "030200",
            "kabupaten_kota": "Kab. Banyumas",
            "kode_kec": "030210",
            "kecamatan": "Kec. Kalibagor",
            "npsn": 20301946,
            "sekolah": "SMP NEGERI 2 KALIBAGOR",
            "bentuk": "Unknown",
            "status": "Negeri",
            "sinkron_terakhir": "05 Feb 2024 14:31:34",
            "sekolah_id_enkrip": "D4353A66A17F33B3455E"
        },
        {
            "kode_prop": "030000",
            "propinsi": "Prov. Jawa Tengah",
            "kode_kab_kota": "030200",
            "kabupaten_kota": "Kab. Banyumas",
            "kode_kec": "030210",
            "kecamatan": "Kec. Kalibagor",
            "npsn": 20301966,
            "sekolah": "SMP NEGERI 3 KALIBAGOR",
            "bentuk": "Unknown",
            "status": "Negeri",
            "sinkron_terakhir": "23 Jan 2024 14:09:47",
            "sekolah_id_enkrip": "0F7AEDF2E01E06C09750"
        },
        {
            "kode_prop": "030000",
            "propinsi": "Prov. Jawa Tengah",
            "kode_kab_kota": "030200",
            "kabupaten_kota": "Kab. Banyumas",
            "kode_kec": "030210",
            "kecamatan": "Kec. Kalibagor",
            "npsn": 20338306,
            "sekolah": "SMP NEGERI 4 KALIBAGOR",
            "bentuk": "Unknown",
            "status": "Negeri",
            "sinkron_terakhir": "02 Feb 2024 06:57:40",
            "sekolah_id_enkrip": "FE7355B54F692574EC51"
        },
        {
            "kode_prop": "030000",
            "propinsi": "Prov. Jawa Tengah",
            "kode_kab_kota": "030200",
            "kabupaten_kota": "Kab. Banyumas",
            "kode_kec": "030210",
            "kecamatan": "Kec. Kalibagor",
            "npsn": 20301889,
            "sekolah": "SMP PGRI KALIBAGOR",
            "bentuk": "Unknown",
            "status": "Swasta",
            "sinkron_terakhir": "04 Feb 2024 20:53:09",
            "sekolah_id_enkrip": "441534BA5D44928FE928"
        },
        {
            "kode_prop": "030000",
            "propinsi": "Prov. Jawa Tengah",
            "kode_kab_kota": "030200",
            "kabupaten_kota": "Kab. Banyumas",
            "kode_kec": "030210",
            "kecamatan": "Kec. Kalibagor",
            "npsn": 20301899,
            "sekolah": "SMKN 1 KALIBAGOR",
            "bentuk": "SMK",
            "status": "Negeri",
            "sinkron_terakhir": "30 Jan 2024 19:49:29",
            "sekolah_id_enkrip": "DC65B72DC20870283B6A"
        },
        {
            "kode_prop": "030000",
            "propinsi": "Prov. Jawa Tengah",
            "kode_kab_kota": "030200",
            "kabupaten_kota": "Kab. Banyumas",
            "kode_kec": "030210",
            "kecamatan": "Kec. Kalibagor",
            "npsn": 20302131,
            "sekolah": "SMKS POLITEKNIK YP3I BANYUMAS",
            "bentuk": "SMK",
            "status": "Swasta",
            "sinkron_terakhir": "04 Feb 2024 20:40:04",
            "sekolah_id_enkrip": "D2EF89D957A3D5794DE2"
        },
        {
            "kode_prop": "030000",
            "propinsi": "Prov. Jawa Tengah",
            "kode_kab_kota": "030200",
            "kabupaten_kota": "Kab. Banyumas",
            "kode_kec": "030210",
            "kecamatan": "Kec. Kalibagor",
            "npsn": "P9998036",
            "sekolah": "PKBM BUDI LUHUR",
            "bentuk": "PKBM",
            "status": "Swasta",
            "sinkron_terakhir": "26 Jan 2024 10:43:30",
            "sekolah_id_enkrip": "C3C613E97DCC09E6564E"
        },
        {
            "kode_prop": "030000",
            "propinsi": "Prov. Jawa Tengah",
            "kode_kab_kota": "030200",
            "kabupaten_kota": "Kab. Banyumas",
            "kode_kec": "030210",
            "kecamatan": "Kec. Kalibagor",
            "npsn": "P2961675",
            "sekolah": "PKBM HARAPAN BANGSA",
            "bentuk": "PKBM",
            "status": "Swasta",
            "sinkron_terakhir": "20 Jan 2024 11:24:18",
            "sekolah_id_enkrip": "00651768B2B947153126"
        },
        {
            "kode_prop": "030000",
            "propinsi": "Prov. Jawa Tengah",
            "kode_kab_kota": "030200",
            "kabupaten_kota": "Kab. Banyumas",
            "kode_kec": "030210",
            "kecamatan": "Kec. Kalibagor",
            "npsn": "P9959724",
            "sekolah": "SKB KALIBAGOR",
            "bentuk": "Unknown",
            "status": "Negeri",
            "sinkron_terakhir": "30 Jan 2024 10:30:32",
            "sekolah_id_enkrip": "B5BCF918060E705CB5ED"
        }
    ]
}