{
    "032700": [
        {
            "kode_prop": "030000",
            "propinsi": "Prov. Jawa Tengah",
            "kode_kab_kota": "032700",
            "kabupaten_kota": "Kab. Pemalang",
            "kode_kec": "032710",
            "kecamatan": "Kec. Petarukan",
            "npsn": 70005358,
            "sekolah": "TK NEGERI PEMBINA PETARUKAN",
            "bentuk": "Unknown",
            "status": "Negeri",
            "sinkron_terakhir": "06 Feb 2024 13:46:53",
            "sekolah_id_enkrip": "BB979F93E09CD0A3C992"
        },
        {
            "kode_prop": "030000",
            "propinsi": "Prov. Jawa Tengah",
            "kode_kab_kota": "032700",
            "kabupaten_kota": "Kab. Pemalang",
            "kode_kec": "032710",
            "kecamatan": "Kec. Petarukan",
            "npsn": 69807456,
            "sekolah": "TK  AL KHOIRIYAH",
            "bentuk": "Unknown",
            "status": "Swasta",
            "sinkron_terakhir": "29 Jan 2024 08:25:38",
            "sekolah_id_enkrip": "8F3317DCC03E72121D0D"
        },
        {
            "kode_prop": "030000",
            "propinsi": "Prov. Jawa Tengah",
            "kode_kab_kota": "032700",
            "kabupaten_kota": "Kab. Pemalang",
            "kode_kec": "032710",
            "kecamatan": "Kec. Petarukan",
            "npsn": 69807596,
            "sekolah": "TK  HANDAYANI O4 TEMUIRENG",
            "bentuk": "Unknown",
            "status": "Swasta",
            "sinkron_terakhir": "04 Feb 2024 22:54:40",
            "sekolah_id_enkrip": "A1E4FC500A3C013EB7A5"
        },
        {
            "kode_prop": "030000",
            "propinsi": "Prov. Jawa Tengah",
            "kode_kab_kota": "032700",
            "kabupaten_kota": "Kab. Pemalang",
            "kode_kec": "032710",
            "kecamatan": "Kec. Petarukan",
            "npsn": 69807597,
            "sekolah": "TK AISYIYAH BUSTANUL ATHFAL KENDALDOYONG",
            "bentuk": "Unknown",
            "status": "Swasta",
            "sinkron_terakhir": "22 Jan 2024 21:40:05",
            "sekolah_id_enkrip": "C62C1E17868ADBF2AB29"
        },
        {
            "kode_prop": "030000",
            "propinsi": "Prov. Jawa Tengah",
            "kode_kab_kota": "032700",
            "kabupaten_kota": "Kab. Pemalang",
            "kode_kec": "032710",
            "kecamatan": "Kec. Petarukan",
            "npsn": 69807570,
            "sekolah": "TK AISYIYAH BUSTANUL ATHFAL KENDALSARI",
            "bentuk": "Unknown",
            "status": "Swasta",
            "sinkron_terakhir": "17 Jan 2024 23:16:43",
            "sekolah_id_enkrip": "01D082850BA9FB4BD78B"
        },
        {
            "kode_prop": "030000",
            "propinsi": "Prov. Jawa Tengah",
            "kode_kab_kota": "032700",
            "kabupaten_kota": "Kab. Pemalang",
            "kode_kec": "032710",
            "kecamatan": "Kec. Petarukan",
            "npsn": 69881031,
            "sekolah": "TK AISYIYAH BUSTANUL ATHFAL PANJUNAN",
            "bentuk": "Unknown",
            "status": "Swasta",
            "sinkron_terakhir": "30 Jan 2024 21:12:45",
            "sekolah_id_enkrip": "E9D8849EB5738F0AFB0F"
        },
        {
            "kode_prop": "030000",
            "propinsi": "Prov. Jawa Tengah",
            "kode_kab_kota": "032700",
            "kabupaten_kota": "Kab. Pemalang",
            "kode_kec": "032710",
            "kecamatan": "Kec. Petarukan",
            "npsn": 69807563,
            "sekolah": "TK AISYIYAH BUSTANUL ATHFAL PETARUKAN",
            "bentuk": "Unknown",
            "status": "Swasta",
            "sinkron_terakhir": "19 Jan 2024 19:04:51",
            "sekolah_id_enkrip": "99C499D394EAFB442612"
        },
        {
            "kode_prop": "030000",
            "propinsi": "Prov. Jawa Tengah",
            "kode_kab_kota": "032700",
            "kabupaten_kota": "Kab. Pemalang",
            "kode_kec": "032710",
            "kecamatan": "Kec. Petarukan",
            "npsn": 69874088,
            "sekolah": "TK ISLAM TERPADU MUTIARA HATI",
            "bentuk": "Unknown",
            "status": "Swasta",
            "sinkron_terakhir": "16 Jan 2024 08:17:00",
            "sekolah_id_enkrip": "E846D9E8527A18F0BDB5"
        },
        {
            "kode_prop": "030000",
            "propinsi": "Prov. Jawa Tengah",
            "kode_kab_kota": "032700",
            "kabupaten_kota": "Kab. Pemalang",
            "kode_kec": "032710",
            "kecamatan": "Kec. Petarukan",
            "npsn": 69910572,
            "sekolah": "TK ISTIQOMAH",
            "bentuk": "Unknown",
            "status": "Swasta",
            "sinkron_terakhir": "04 Feb 2024 14:52:13",
            "sekolah_id_enkrip": "6C4AEEC871A441587E91"
        },
        {
            "kode_prop": "030000",
            "propinsi": "Prov. Jawa Tengah",
            "kode_kab_kota": "032700",
            "kabupaten_kota": "Kab. Pemalang",
            "kode_kec": "032710",
            "kecamatan": "Kec. Petarukan",
            "npsn": 69807586,
            "sekolah": "TK IT PERMATA BUNDA",
            "bentuk": "Unknown",
            "status": "Swasta",
            "sinkron_terakhir": "06 Feb 2024 11:22:23",
            "sekolah_id_enkrip": "593288D2EE95DE2B58C0"
        },
        {
            "kode_prop": "030000",
            "propinsi": "Prov. Jawa Tengah",
            "kode_kab_kota": "032700",
            "kabupaten_kota": "Kab. Pemalang",
            "kode_kec": "032710",
            "kecamatan": "Kec. Petarukan",
            "npsn": 69807571,
            "sekolah": "TK MUSLIMAT NU BUANA KARTIKA",
            "bentuk": "Unknown",
            "status": "Swasta",
            "sinkron_terakhir": "24 Jan 2024 10:40:37",
            "sekolah_id_enkrip": "0690FF4AA227C19CA0C2"
        },
        {
            "kode_prop": "030000",
            "propinsi": "Prov. Jawa Tengah",
            "kode_kab_kota": "032700",
            "kabupaten_kota": "Kab. Pemalang",
            "kode_kec": "032710",
            "kecamatan": "Kec. Petarukan",
            "npsn": 69807602,
            "sekolah": "TK MUSLIMAT NU BUANA KARTIKA 02 KENDALREJO",
            "bentuk": "Unknown",
            "status": "Swasta",
            "sinkron_terakhir": "13 Jan 2024 20:11:46",
            "sekolah_id_enkrip": "8722A1822164F81EC3FF"
        },
        {
            "kode_prop": "030000",
            "propinsi": "Prov. Jawa Tengah",
            "kode_kab_kota": "032700",
            "kabupaten_kota": "Kab. Pemalang",
            "kode_kec": "032710",
            "kecamatan": "Kec. Petarukan",
            "npsn": 69807589,
            "sekolah": "TK MUSLIMAT NU MIFTAHUL ULUM",
            "bentuk": "Unknown",
            "status": "Swasta",
            "sinkron_terakhir": "27 Jan 2024 05:50:00",
            "sekolah_id_enkrip": "95EC9CCF6D4C1622B02F"
        },
        {
            "kode_prop": "030000",
            "propinsi": "Prov. Jawa Tengah",
            "kode_kab_kota": "032700",
            "kabupaten_kota": "Kab. Pemalang",
            "kode_kec": "032710",
            "kecamatan": "Kec. Petarukan",
            "npsn": 69807561,
            "sekolah": "TK MUSLIMAT NU NURUL IMAN PETANJUNGAN",
            "bentuk": "Unknown",
            "status": "Swasta",
            "sinkron_terakhir": "16 Jan 2024 06:21:12",
            "sekolah_id_enkrip": "893E9572E6040FAE9C1F"
        },
        {
            "kode_prop": "030000",
            "propinsi": "Prov. Jawa Tengah",
            "kode_kab_kota": "032700",
            "kabupaten_kota": "Kab. Pemalang",
            "kode_kec": "032710",
            "kecamatan": "Kec. Petarukan",
            "npsn": 69807517,
            "sekolah": "TK MUSLIMAT NU PANJUNAN",
            "bentuk": "Unknown",
            "status": "Swasta",
            "sinkron_terakhir": "31 Oct 2023 11:23:21",
            "sekolah_id_enkrip": "59EA81BB4E7D6B7D6932"
        },
        {
            "kode_prop": "030000",
            "propinsi": "Prov. Jawa Tengah",
            "kode_kab_kota": "032700",
            "kabupaten_kota": "Kab. Pemalang",
            "kode_kec": "032710",
            "kecamatan": "Kec. Petarukan",
            "npsn": 69807524,
            "sekolah": "TK MUSLIMAT NU PETARUKAN",
            "bentuk": "Unknown",
            "status": "Swasta",
            "sinkron_terakhir": "18 Jan 2024 13:18:28",
            "sekolah_id_enkrip": "753306D33FB267BAE918"
        },
        {
            "kode_prop": "030000",
            "propinsi": "Prov. Jawa Tengah",
            "kode_kab_kota": "032700",
            "kabupaten_kota": "Kab. Pemalang",
            "kode_kec": "032710",
            "kecamatan": "Kec. Petarukan",
            "npsn": 69892133,
            "sekolah": "TK MUSLIMAT NU SABIILIR  ROSYAD",
            "bentuk": "Unknown",
            "status": "Swasta",
            "sinkron_terakhir": "18 Jan 2024 12:50:28",
            "sekolah_id_enkrip": "5B9161014DBBDE91DF2B"
        },
        {
            "kode_prop": "030000",
            "propinsi": "Prov. Jawa Tengah",
            "kode_kab_kota": "032700",
            "kabupaten_kota": "Kab. Pemalang",
            "kode_kec": "032710",
            "kecamatan": "Kec. Petarukan",
            "npsn": 70031303,
            "sekolah": "TK MUSLIMAT PANJUNAN SELATAN",
            "bentuk": "Unknown",
            "status": "Swasta",
            "sinkron_terakhir": "01 Feb 2024 10:03:48",
            "sekolah_id_enkrip": "81043F868D7451CD493B"
        },
        {
            "kode_prop": "030000",
            "propinsi": "Prov. Jawa Tengah",
            "kode_kab_kota": "032700",
            "kabupaten_kota": "Kab. Pemalang",
            "kode_kec": "032710",
            "kecamatan": "Kec. Petarukan",
            "npsn": 69909331,
            "sekolah": "TK PELITA HATI",
            "bentuk": "Unknown",
            "status": "Swasta",
            "sinkron_terakhir": "14 Jan 2024 21:58:47",
            "sekolah_id_enkrip": "28FB92E0F6DDBD07F25D"
        },
        {
            "kode_prop": "030000",
            "propinsi": "Prov. Jawa Tengah",
            "kode_kab_kota": "032700",
            "kabupaten_kota": "Kab. Pemalang",
            "kode_kec": "032710",
            "kecamatan": "Kec. Petarukan",
            "npsn": 69807532,
            "sekolah": "TK PERTIWI 01 PETANJUNGAN",
            "bentuk": "Unknown",
            "status": "Swasta",
            "sinkron_terakhir": "04 Feb 2024 21:13:51",
            "sekolah_id_enkrip": "0BFFAC3FE629ACDD5046"
        },
        {
            "kode_prop": "030000",
            "propinsi": "Prov. Jawa Tengah",
            "kode_kab_kota": "032700",
            "kabupaten_kota": "Kab. Pemalang",
            "kode_kec": "032710",
            "kecamatan": "Kec. Petarukan",
            "npsn": 69807606,
            "sekolah": "TK PERTIWI 01 PETARUKAN",
            "bentuk": "Unknown",
            "status": "Swasta",
            "sinkron_terakhir": "28 Jan 2024 11:26:45",
            "sekolah_id_enkrip": "17632D3307C74D74853A"
        },
        {
            "kode_prop": "030000",
            "propinsi": "Prov. Jawa Tengah",
            "kode_kab_kota": "032700",
            "kabupaten_kota": "Kab. Pemalang",
            "kode_kec": "032710",
            "kecamatan": "Kec. Petarukan",
            "npsn": 69881030,
            "sekolah": "TK PERTIWI 01 SERANG",
            "bentuk": "Unknown",
            "status": "Swasta",
            "sinkron_terakhir": "19 Dec 2023 22:48:54",
            "sekolah_id_enkrip": "5DBB6D92DF0F673A7130"
        },
        {
            "kode_prop": "030000",
            "propinsi": "Prov. Jawa Tengah",
            "kode_kab_kota": "032700",
            "kabupaten_kota": "Kab. Pemalang",
            "kode_kec": "032710",
            "kecamatan": "Kec. Petarukan",
            "npsn": 69874087,
            "sekolah": "TK PERTIWI 01 WIDODAREN",
            "bentuk": "Unknown",
            "status": "Swasta",
            "sinkron_terakhir": "29 Jan 2024 12:52:08",
            "sekolah_id_enkrip": "475F13C27DC7E474365E"
        },
        {
            "kode_prop": "030000",
            "propinsi": "Prov. Jawa Tengah",
            "kode_kab_kota": "032700",
            "kabupaten_kota": "Kab. Pemalang",
            "kode_kec": "032710",
            "kecamatan": "Kec. Petarukan",
            "npsn": 69807547,
            "sekolah": "TK PERTIWI 02  PETARUKAN",
            "bentuk": "Unknown",
            "status": "Swasta",
            "sinkron_terakhir": "23 Jan 2024 09:27:23",
            "sekolah_id_enkrip": "AB96398145E6C04CD24D"
        },
        {
            "kode_prop": "030000",
            "propinsi": "Prov. Jawa Tengah",
            "kode_kab_kota": "032700",
            "kabupaten_kota": "Kab. Pemalang",
            "kode_kec": "032710",
            "kecamatan": "Kec. Petarukan",
            "npsn": 69807475,
            "sekolah": "TK PERTIWI 02 PETANJUNGAN",
            "bentuk": "Unknown",
            "status": "Swasta",
            "sinkron_terakhir": "15 Jan 2024 15:23:57",
            "sekolah_id_enkrip": "D63FD9DE6785D298CDF5"
        },
        {
            "kode_prop": "030000",
            "propinsi": "Prov. Jawa Tengah",
            "kode_kab_kota": "032700",
            "kabupaten_kota": "Kab. Pemalang",
            "kode_kec": "032710",
            "kecamatan": "Kec. Petarukan",
            "npsn": 69807438,
            "sekolah": "TK PERTIWI 02 SERANG",
            "bentuk": "Unknown",
            "status": "Swasta",
            "sinkron_terakhir": "15 Jan 2024 19:00:54",
            "sekolah_id_enkrip": "25E506DCAF6A6093C911"
        },
        {
            "kode_prop": "030000",
            "propinsi": "Prov. Jawa Tengah",
            "kode_kab_kota": "032700",
            "kabupaten_kota": "Kab. Pemalang",
            "kode_kec": "032710",
            "kecamatan": "Kec. Petarukan",
            "npsn": 69807530,
            "sekolah": "TK PERTIWI 02 WIDODAREN",
            "bentuk": "Unknown",
            "status": "Swasta",
            "sinkron_terakhir": "14 Jan 2024 20:00:02",
            "sekolah_id_enkrip": "9639DA594F1C8D36209D"
        },
        {
            "kode_prop": "030000",
            "propinsi": "Prov. Jawa Tengah",
            "kode_kab_kota": "032700",
            "kabupaten_kota": "Kab. Pemalang",
            "kode_kec": "032710",
            "kecamatan": "Kec. Petarukan",
            "npsn": 69904540,
            "sekolah": "TK PERTIWI BULU",
            "bentuk": "Unknown",
            "status": "Swasta",
            "sinkron_terakhir": "12 Jan 2024 19:03:47",
            "sekolah_id_enkrip": "4FDE061A31F0B016D267"
        },
        {
            "kode_prop": "030000",
            "propinsi": "Prov. Jawa Tengah",
            "kode_kab_kota": "032700",
            "kabupaten_kota": "Kab. Pemalang",
            "kode_kec": "032710",
            "kecamatan": "Kec. Petarukan",
            "npsn": 69905849,
            "sekolah": "TK PERTIWI DESA NYAMPLUNGSARI",
            "bentuk": "Unknown",
            "status": "Swasta",
            "sinkron_terakhir": "15 Jan 2024 04:49:13",
            "sekolah_id_enkrip": "2DC7F5074F28030EC4B8"
        },
        {
            "kode_prop": "030000",
            "propinsi": "Prov. Jawa Tengah",
            "kode_kab_kota": "032700",
            "kabupaten_kota": "Kab. Pemalang",
            "kode_kec": "032710",
            "kecamatan": "Kec. Petarukan",
            "npsn": 69807436,
            "sekolah": "TK PERTIWI ISER",
            "bentuk": "Unknown",
            "status": "Swasta",
            "sinkron_terakhir": "14 Jan 2024 22:33:02",
            "sekolah_id_enkrip": "2DBD5D7B24A80DB2F739"
        },
        {
            "kode_prop": "030000",
            "propinsi": "Prov. Jawa Tengah",
            "kode_kab_kota": "032700",
            "kabupaten_kota": "Kab. Pemalang",
            "kode_kec": "032710",
            "kecamatan": "Kec. Petarukan",
            "npsn": 69807540,
            "sekolah": "TK PERTIWI KALIRANDU",
            "bentuk": "Unknown",
            "status": "Swasta",
            "sinkron_terakhir": "01 Feb 2024 11:57:29",
            "sekolah_id_enkrip": "149B5E0EFEBB209F5D07"
        },
        {
            "kode_prop": "030000",
            "propinsi": "Prov. Jawa Tengah",
            "kode_kab_kota": "032700",
            "kabupaten_kota": "Kab. Pemalang",
            "kode_kec": "032710",
            "kecamatan": "Kec. Petarukan",
            "npsn": 69807558,
            "sekolah": "TK PERTIWI KARANGASEM",
            "bentuk": "Unknown",
            "status": "Swasta",
            "sinkron_terakhir": "18 Jan 2024 21:58:06",
            "sekolah_id_enkrip": "F7A46C4AD4BCA2AD417E"
        },
        {
            "kode_prop": "030000",
            "propinsi": "Prov. Jawa Tengah",
            "kode_kab_kota": "032700",
            "kabupaten_kota": "Kab. Pemalang",
            "kode_kec": "032710",
            "kecamatan": "Kec. Petarukan",
            "npsn": 69807580,
            "sekolah": "TK PERTIWI KENDALDOYONG",
            "bentuk": "Unknown",
            "status": "Swasta",
            "sinkron_terakhir": "23 Jan 2024 21:59:58",
            "sekolah_id_enkrip": "644ACB9ACA46A4DA8F12"
        },
        {
            "kode_prop": "030000",
            "propinsi": "Prov. Jawa Tengah",
            "kode_kab_kota": "032700",
            "kabupaten_kota": "Kab. Pemalang",
            "kode_kec": "032710",
            "kecamatan": "Kec. Petarukan",
            "npsn": 69807579,
            "sekolah": "TK PERTIWI KENDALSARI",
            "bentuk": "Unknown",
            "status": "Swasta",
            "sinkron_terakhir": "06 Feb 2024 10:30:38",
            "sekolah_id_enkrip": "CAC6D659F29812351751"
        },
        {
            "kode_prop": "030000",
            "propinsi": "Prov. Jawa Tengah",
            "kode_kab_kota": "032700",
            "kabupaten_kota": "Kab. Pemalang",
            "kode_kec": "032710",
            "kecamatan": "Kec. Petarukan",
            "npsn": 69807478,
            "sekolah": "TK PERTIWI KLAREYAN",
            "bentuk": "Unknown",
            "status": "Swasta",
            "sinkron_terakhir": "03 Feb 2024 00:23:45",
            "sekolah_id_enkrip": "2F5EFC517A699475B34C"
        },
        {
            "kode_prop": "030000",
            "propinsi": "Prov. Jawa Tengah",
            "kode_kab_kota": "032700",
            "kabupaten_kota": "Kab. Pemalang",
            "kode_kec": "032710",
            "kecamatan": "Kec. Petarukan",
            "npsn": 69807447,
            "sekolah": "TK PERTIWI LONING BARAT",
            "bentuk": "Unknown",
            "status": "Swasta",
            "sinkron_terakhir": "13 Jan 2024 22:39:22",
            "sekolah_id_enkrip": "86DE9766365537B63506"
        },
        {
            "kode_prop": "030000",
            "propinsi": "Prov. Jawa Tengah",
            "kode_kab_kota": "032700",
            "kabupaten_kota": "Kab. Pemalang",
            "kode_kec": "032710",
            "kecamatan": "Kec. Petarukan",
            "npsn": 69807451,
            "sekolah": "TK PERTIWI LONING TIMUR",
            "bentuk": "Unknown",
            "status": "Swasta",
            "sinkron_terakhir": "19 Jan 2024 16:32:55",
            "sekolah_id_enkrip": "C204762E822D20AD0650"
        },
        {
            "kode_prop": "030000",
            "propinsi": "Prov. Jawa Tengah",
            "kode_kab_kota": "032700",
            "kabupaten_kota": "Kab. Pemalang",
            "kode_kec": "032710",
            "kecamatan": "Kec. Petarukan",
            "npsn": 69807545,
            "sekolah": "TK PERTIWI PEGUNDAN",
            "bentuk": "Unknown",
            "status": "Swasta",
            "sinkron_terakhir": "30 Jan 2024 23:04:33",
            "sekolah_id_enkrip": "AE372C37E1C622ABFF2E"
        },
        {
            "kode_prop": "030000",
            "propinsi": "Prov. Jawa Tengah",
            "kode_kab_kota": "032700",
            "kabupaten_kota": "Kab. Pemalang",
            "kode_kec": "032710",
            "kecamatan": "Kec. Petarukan",
            "npsn": 69807566,
            "sekolah": "TK PERTIWI PESUCEN",
            "bentuk": "Unknown",
            "status": "Swasta",
            "sinkron_terakhir": "02 Feb 2024 06:49:00",
            "sekolah_id_enkrip": "47CA3A2513BA58288F3A"
        },
        {
            "kode_prop": "030000",
            "propinsi": "Prov. Jawa Tengah",
            "kode_kab_kota": "032700",
            "kabupaten_kota": "Kab. Pemalang",
            "kode_kec": "032710",
            "kecamatan": "Kec. Petarukan",
            "npsn": 69807582,
            "sekolah": "TK PERTIWI TEGALMLATI",
            "bentuk": "Unknown",
            "status": "Swasta",
            "sinkron_terakhir": "17 Jan 2024 13:52:08",
            "sekolah_id_enkrip": "D125D1D3A01244F5779F"
        },
        {
            "kode_prop": "030000",
            "propinsi": "Prov. Jawa Tengah",
            "kode_kab_kota": "032700",
            "kabupaten_kota": "Kab. Pemalang",
            "kode_kec": "032710",
            "kecamatan": "Kec. Petarukan",
            "npsn": 69807614,
            "sekolah": "TK RA KARTINI KENDALSARI",
            "bentuk": "Unknown",
            "status": "Swasta",
            "sinkron_terakhir": "18 Jan 2024 12:45:22",
            "sekolah_id_enkrip": "DEC03DC89819A08A0139"
        },
        {
            "kode_prop": "030000",
            "propinsi": "Prov. Jawa Tengah",
            "kode_kab_kota": "032700",
            "kabupaten_kota": "Kab. Pemalang",
            "kode_kec": "032710",
            "kecamatan": "Kec. Petarukan",
            "npsn": 69871462,
            "sekolah": "TK TERPADU AISYIYAH PETARUKAN",
            "bentuk": "Unknown",
            "status": "Swasta",
            "sinkron_terakhir": "02 Feb 2024 05:53:12",
            "sekolah_id_enkrip": "66085C91D29F91C15DD0"
        },
        {
            "kode_prop": "030000",
            "propinsi": "Prov. Jawa Tengah",
            "kode_kab_kota": "032700",
            "kabupaten_kota": "Kab. Pemalang",
            "kode_kec": "032710",
            "kecamatan": "Kec. Petarukan",
            "npsn": 69873612,
            "sekolah": "TKIT MUTHIA KALIRANDU",
            "bentuk": "Unknown",
            "status": "Swasta",
            "sinkron_terakhir": "13 Jan 2024 09:41:39",
            "sekolah_id_enkrip": "782A3AB14962B8019573"
        },
        {
            "kode_prop": "030000",
            "propinsi": "Prov. Jawa Tengah",
            "kode_kab_kota": "032700",
            "kabupaten_kota": "Kab. Pemalang",
            "kode_kec": "032710",
            "kecamatan": "Kec. Petarukan",
            "npsn": 69991652,
            "sekolah": "KB AL HIKMAH KLAREYAN",
            "bentuk": "Unknown",
            "status": "Swasta",
            "sinkron_terakhir": "23 Jan 2024 19:19:49",
            "sekolah_id_enkrip": "E88717890EE8E3BC5396"
        },
        {
            "kode_prop": "030000",
            "propinsi": "Prov. Jawa Tengah",
            "kode_kab_kota": "032700",
            "kabupaten_kota": "Kab. Pemalang",
            "kode_kec": "032710",
            "kecamatan": "Kec. Petarukan",
            "npsn": 69807776,
            "sekolah": "KB BAITURROHMAH",
            "bentuk": "Unknown",
            "status": "Swasta",
            "sinkron_terakhir": "19 Jan 2024 22:27:07",
            "sekolah_id_enkrip": "2D1AD63ED7E323D4E721"
        },
        {
            "kode_prop": "030000",
            "propinsi": "Prov. Jawa Tengah",
            "kode_kab_kota": "032700",
            "kabupaten_kota": "Kab. Pemalang",
            "kode_kec": "032710",
            "kecamatan": "Kec. Petarukan",
            "npsn": 69807790,
            "sekolah": "KB BAITUSSALAM",
            "bentuk": "Unknown",
            "status": "Swasta",
            "sinkron_terakhir": "18 Oct 2023 21:01:13",
            "sekolah_id_enkrip": "7307181977622758AAF2"
        },
        {
            "kode_prop": "030000",
            "propinsi": "Prov. Jawa Tengah",
            "kode_kab_kota": "032700",
            "kabupaten_kota": "Kab. Pemalang",
            "kode_kec": "032710",
            "kecamatan": "Kec. Petarukan",
            "npsn": 69871492,
            "sekolah": "KB BHAKTI PERTIWI",
            "bentuk": "Unknown",
            "status": "Swasta",
            "sinkron_terakhir": "30 Nov 2023 22:34:23",
            "sekolah_id_enkrip": "93E2ABFB77AEE513E55D"
        },
        {
            "kode_prop": "030000",
            "propinsi": "Prov. Jawa Tengah",
            "kode_kab_kota": "032700",
            "kabupaten_kota": "Kab. Pemalang",
            "kode_kec": "032710",
            "kecamatan": "Kec. Petarukan",
            "npsn": 69875497,
            "sekolah": "KB BIRUL WALIDAIN",
            "bentuk": "Unknown",
            "status": "Swasta",
            "sinkron_terakhir": "21 Jan 2024 06:39:19",
            "sekolah_id_enkrip": "F527101679012C3BA05D"
        },
        {
            "kode_prop": "030000",
            "propinsi": "Prov. Jawa Tengah",
            "kode_kab_kota": "032700",
            "kabupaten_kota": "Kab. Pemalang",
            "kode_kec": "032710",
            "kecamatan": "Kec. Petarukan",
            "npsn": 69972649,
            "sekolah": "KB BUAH HATI",
            "bentuk": "Unknown",
            "status": "Swasta",
            "sinkron_terakhir": "21 Aug 2023 05:51:30",
            "sekolah_id_enkrip": "6823E54F3CF18412E022"
        },
        {
            "kode_prop": "030000",
            "propinsi": "Prov. Jawa Tengah",
            "kode_kab_kota": "032700",
            "kabupaten_kota": "Kab. Pemalang",
            "kode_kec": "032710",
            "kecamatan": "Kec. Petarukan",
            "npsn": 69807836,
            "sekolah": "KB CATUR BUDI LESTARI",
            "bentuk": "Unknown",
            "status": "Swasta",
            "sinkron_terakhir": "16 Oct 2023 09:38:24",
            "sekolah_id_enkrip": "FD68EB49915FB5EEC3E0"
        },
        {
            "kode_prop": "030000",
            "propinsi": "Prov. Jawa Tengah",
            "kode_kab_kota": "032700",
            "kabupaten_kota": "Kab. Pemalang",
            "kode_kec": "032710",
            "kecamatan": "Kec. Petarukan",
            "npsn": 69871487,
            "sekolah": "KB DAARUN NAJA",
            "bentuk": "Unknown",
            "status": "Swasta",
            "sinkron_terakhir": "20 Oct 2023 09:03:57",
            "sekolah_id_enkrip": "7ACB2BDA1C008201BA24"
        },
        {
            "kode_prop": "030000",
            "propinsi": "Prov. Jawa Tengah",
            "kode_kab_kota": "032700",
            "kabupaten_kota": "Kab. Pemalang",
            "kode_kec": "032710",
            "kecamatan": "Kec. Petarukan",
            "npsn": 69807867,
            "sekolah": "KB DAARUSH SHOBAR",
            "bentuk": "Unknown",
            "status": "Swasta",
            "sinkron_terakhir": "31 Dec 2023 21:39:02",
            "sekolah_id_enkrip": "CC457FCEFF1D11285F45"
        },
        {
            "kode_prop": "030000",
            "propinsi": "Prov. Jawa Tengah",
            "kode_kab_kota": "032700",
            "kabupaten_kota": "Kab. Pemalang",
            "kode_kec": "032710",
            "kecamatan": "Kec. Petarukan",
            "npsn": 69807886,
            "sekolah": "KB HIDAYATUL MUBTADIIN",
            "bentuk": "Unknown",
            "status": "Swasta",
            "sinkron_terakhir": "19 Nov 2023 21:17:28",
            "sekolah_id_enkrip": "2E2E1A1C7DA6D53E68ED"
        },
        {
            "kode_prop": "030000",
            "propinsi": "Prov. Jawa Tengah",
            "kode_kab_kota": "032700",
            "kabupaten_kota": "Kab. Pemalang",
            "kode_kec": "032710",
            "kecamatan": "Kec. Petarukan",
            "npsn": 69930286,
            "sekolah": "KB KASIH IBU",
            "bentuk": "Unknown",
            "status": "Swasta",
            "sinkron_terakhir": "24 Jan 2024 14:53:21",
            "sekolah_id_enkrip": "6DEB878662DD56239067"
        },
        {
            "kode_prop": "030000",
            "propinsi": "Prov. Jawa Tengah",
            "kode_kab_kota": "032700",
            "kabupaten_kota": "Kab. Pemalang",
            "kode_kec": "032710",
            "kecamatan": "Kec. Petarukan",
            "npsn": 69871490,
            "sekolah": "KB MANDIRI",
            "bentuk": "Unknown",
            "status": "Swasta",
            "sinkron_terakhir": "24 Jan 2024 10:37:11",
            "sekolah_id_enkrip": "333F279E4EDFF95405DB"
        },
        {
            "kode_prop": "030000",
            "propinsi": "Prov. Jawa Tengah",
            "kode_kab_kota": "032700",
            "kabupaten_kota": "Kab. Pemalang",
            "kode_kec": "032710",
            "kecamatan": "Kec. Petarukan",
            "npsn": 69807914,
            "sekolah": "KB MEKAR CERIA",
            "bentuk": "Unknown",
            "status": "Swasta",
            "sinkron_terakhir": "24 Jan 2024 09:12:14",
            "sekolah_id_enkrip": "1C52ADD4E8F5D8D54123"
        },
        {
            "kode_prop": "030000",
            "propinsi": "Prov. Jawa Tengah",
            "kode_kab_kota": "032700",
            "kabupaten_kota": "Kab. Pemalang",
            "kode_kec": "032710",
            "kecamatan": "Kec. Petarukan",
            "npsn": 69807713,
            "sekolah": "KB MELATI",
            "bentuk": "Unknown",
            "status": "Swasta",
            "sinkron_terakhir": "13 Jan 2024 03:22:14",
            "sekolah_id_enkrip": "51710ED60B4E94B69B03"
        },
        {
            "kode_prop": "030000",
            "propinsi": "Prov. Jawa Tengah",
            "kode_kab_kota": "032700",
            "kabupaten_kota": "Kab. Pemalang",
            "kode_kec": "032710",
            "kecamatan": "Kec. Petarukan",
            "npsn": 69991616,
            "sekolah": "KB MIFTAHUL HUDA",
            "bentuk": "Unknown",
            "status": "Swasta",
            "sinkron_terakhir": "30 Oct 2023 00:02:48",
            "sekolah_id_enkrip": "22194A35C14982D1361D"
        },
        {
            "kode_prop": "030000",
            "propinsi": "Prov. Jawa Tengah",
            "kode_kab_kota": "032700",
            "kabupaten_kota": "Kab. Pemalang",
            "kode_kec": "032710",
            "kecamatan": "Kec. Petarukan",
            "npsn": 69807765,
            "sekolah": "KB MUALLIMIN",
            "bentuk": "Unknown",
            "status": "Swasta",
            "sinkron_terakhir": "24 Jan 2024 14:30:59",
            "sekolah_id_enkrip": "D45F59F91EEE86FA4CF9"
        },
        {
            "kode_prop": "030000",
            "propinsi": "Prov. Jawa Tengah",
            "kode_kab_kota": "032700",
            "kabupaten_kota": "Kab. Pemalang",
            "kode_kec": "032710",
            "kecamatan": "Kec. Petarukan",
            "npsn": 69918376,
            "sekolah": "KB MUSLIMAT NU AL MUKHOYYAROH",
            "bentuk": "Unknown",
            "status": "Swasta",
            "sinkron_terakhir": "06 Aug 2023 17:18:43",
            "sekolah_id_enkrip": "283D8169909A8FF3F8DF"
        },
        {
            "kode_prop": "030000",
            "propinsi": "Prov. Jawa Tengah",
            "kode_kab_kota": "032700",
            "kabupaten_kota": "Kab. Pemalang",
            "kode_kec": "032710",
            "kecamatan": "Kec. Petarukan",
            "npsn": 69807742,
            "sekolah": "KB MUSLIMAT NU MIFTAHUL ULUM I PETARUKAN",
            "bentuk": "Unknown",
            "status": "Swasta",
            "sinkron_terakhir": "18 Jan 2024 05:28:50",
            "sekolah_id_enkrip": "A0563E97590EFD0FA7A5"
        },
        {
            "kode_prop": "030000",
            "propinsi": "Prov. Jawa Tengah",
            "kode_kab_kota": "032700",
            "kabupaten_kota": "Kab. Pemalang",
            "kode_kec": "032710",
            "kecamatan": "Kec. Petarukan",
            "npsn": 69807727,
            "sekolah": "KB MUSLIMAT NU MIFTAKHUL ULUM 02 LONING",
            "bentuk": "Unknown",
            "status": "Swasta",
            "sinkron_terakhir": "18 Jan 2024 21:07:44",
            "sekolah_id_enkrip": "803E77085D5EAC8F3346"
        },
        {
            "kode_prop": "030000",
            "propinsi": "Prov. Jawa Tengah",
            "kode_kab_kota": "032700",
            "kabupaten_kota": "Kab. Pemalang",
            "kode_kec": "032710",
            "kecamatan": "Kec. Petarukan",
            "npsn": 69918358,
            "sekolah": "KB MUSLIMAT NU PANJUNAN",
            "bentuk": "Unknown",
            "status": "Swasta",
            "sinkron_terakhir": "24 Nov 2023 13:56:13",
            "sekolah_id_enkrip": "6706D79F6B65C8C00CB2"
        },
        {
            "kode_prop": "030000",
            "propinsi": "Prov. Jawa Tengah",
            "kode_kab_kota": "032700",
            "kabupaten_kota": "Kab. Pemalang",
            "kode_kec": "032710",
            "kecamatan": "Kec. Petarukan",
            "npsn": 69871485,
            "sekolah": "KB PELITA HATI",
            "bentuk": "Unknown",
            "status": "Swasta",
            "sinkron_terakhir": "12 Nov 2023 20:41:44",
            "sekolah_id_enkrip": "5D04EF80F1B00879D3BD"
        },
        {
            "kode_prop": "030000",
            "propinsi": "Prov. Jawa Tengah",
            "kode_kab_kota": "032700",
            "kabupaten_kota": "Kab. Pemalang",
            "kode_kec": "032710",
            "kecamatan": "Kec. Petarukan",
            "npsn": 69807722,
            "sekolah": "KB SEKAR TANJUNG",
            "bentuk": "Unknown",
            "status": "Swasta",
            "sinkron_terakhir": "26 Jan 2024 19:44:04",
            "sekolah_id_enkrip": "ADD146BF70B97081F49C"
        },
        {
            "kode_prop": "030000",
            "propinsi": "Prov. Jawa Tengah",
            "kode_kab_kota": "032700",
            "kabupaten_kota": "Kab. Pemalang",
            "kode_kec": "032710",
            "kecamatan": "Kec. Petarukan",
            "npsn": 69807705,
            "sekolah": "KB TERPADU AISYIYAH",
            "bentuk": "Unknown",
            "status": "Swasta",
            "sinkron_terakhir": "24 Aug 2023 21:13:42",
            "sekolah_id_enkrip": "27B980024057693841D7"
        },
        {
            "kode_prop": "030000",
            "propinsi": "Prov. Jawa Tengah",
            "kode_kab_kota": "032700",
            "kabupaten_kota": "Kab. Pemalang",
            "kode_kec": "032710",
            "kecamatan": "Kec. Petarukan",
            "npsn": 69904445,
            "sekolah": "KB TERPADU MUSLIMAT NU PETARUKAN",
            "bentuk": "Unknown",
            "status": "Swasta",
            "sinkron_terakhir": "01 Aug 2023 18:01:16",
            "sekolah_id_enkrip": "6C4037F3FC44E21C2C16"
        },
        {
            "kode_prop": "030000",
            "propinsi": "Prov. Jawa Tengah",
            "kode_kab_kota": "032700",
            "kabupaten_kota": "Kab. Pemalang",
            "kode_kec": "032710",
            "kecamatan": "Kec. Petarukan",
            "npsn": 69871491,
            "sekolah": "KB TUNAS BANGSA",
            "bentuk": "Unknown",
            "status": "Swasta",
            "sinkron_terakhir": "24 Jan 2024 03:59:45",
            "sekolah_id_enkrip": "265131C670385C7B50AF"
        },
        {
            "kode_prop": "030000",
            "propinsi": "Prov. Jawa Tengah",
            "kode_kab_kota": "032700",
            "kabupaten_kota": "Kab. Pemalang",
            "kode_kec": "032710",
            "kecamatan": "Kec. Petarukan",
            "npsn": 69807842,
            "sekolah": "KB WARDATUL JANNAH",
            "bentuk": "Unknown",
            "status": "Swasta",
            "sinkron_terakhir": "24 Jan 2024 09:29:58",
            "sekolah_id_enkrip": "0DF0EABAB2968E324CC2"
        },
        {
            "kode_prop": "030000",
            "propinsi": "Prov. Jawa Tengah",
            "kode_kab_kota": "032700",
            "kabupaten_kota": "Kab. Pemalang",
            "kode_kec": "032710",
            "kecamatan": "Kec. Petarukan",
            "npsn": 69871493,
            "sekolah": "KBI AL-QOLAM",
            "bentuk": "Unknown",
            "status": "Swasta",
            "sinkron_terakhir": "02 Aug 2023 16:19:39",
            "sekolah_id_enkrip": "CF39A3FA7842C6560135"
        },
        {
            "kode_prop": "030000",
            "propinsi": "Prov. Jawa Tengah",
            "kode_kab_kota": "032700",
            "kabupaten_kota": "Kab. Pemalang",
            "kode_kec": "032710",
            "kecamatan": "Kec. Petarukan",
            "npsn": 69871486,
            "sekolah": "KBIT MUTHIA",
            "bentuk": "Unknown",
            "status": "Swasta",
            "sinkron_terakhir": "07 Dec 2023 12:19:51",
            "sekolah_id_enkrip": "CD1EFAF8792221300288"
        },
        {
            "kode_prop": "030000",
            "propinsi": "Prov. Jawa Tengah",
            "kode_kab_kota": "032700",
            "kabupaten_kota": "Kab. Pemalang",
            "kode_kec": "032710",
            "kecamatan": "Kec. Petarukan",
            "npsn": 69967858,
            "sekolah": "KBIT MUTIARA SREGEP",
            "bentuk": "Unknown",
            "status": "Swasta",
            "sinkron_terakhir": "25 Jan 2024 22:52:13",
            "sekolah_id_enkrip": "F0D76C5C14BB384B8420"
        },
        {
            "kode_prop": "030000",
            "propinsi": "Prov. Jawa Tengah",
            "kode_kab_kota": "032700",
            "kabupaten_kota": "Kab. Pemalang",
            "kode_kec": "032710",
            "kecamatan": "Kec. Petarukan",
            "npsn": 69807918,
            "sekolah": "KBIT PERMATA BUNDA",
            "bentuk": "Unknown",
            "status": "Swasta",
            "sinkron_terakhir": "24 Oct 2023 22:46:09",
            "sekolah_id_enkrip": "AB31D33EFDC16AA2135E"
        },
        {
            "kode_prop": "030000",
            "propinsi": "Prov. Jawa Tengah",
            "kode_kab_kota": "032700",
            "kabupaten_kota": "Kab. Pemalang",
            "kode_kec": "032710",
            "kecamatan": "Kec. Petarukan",
            "npsn": 69807799,
            "sekolah": "TPA IT PERMATA BUNDA",
            "bentuk": "Unknown",
            "status": "Swasta",
            "sinkron_terakhir": "31 Jan 2024 08:53:09",
            "sekolah_id_enkrip": "9C30B938255E06139AEA"
        },
        {
            "kode_prop": "030000",
            "propinsi": "Prov. Jawa Tengah",
            "kode_kab_kota": "032700",
            "kabupaten_kota": "Kab. Pemalang",
            "kode_kec": "032710",
            "kecamatan": "Kec. Petarukan",
            "npsn": 69871503,
            "sekolah": "TPA MUTHIA",
            "bentuk": "Unknown",
            "status": "Swasta",
            "sinkron_terakhir": "08 Dec 2023 08:24:47",
            "sekolah_id_enkrip": "9B552C0F786507A18E62"
        },
        {
            "kode_prop": "030000",
            "propinsi": "Prov. Jawa Tengah",
            "kode_kab_kota": "032700",
            "kabupaten_kota": "Kab. Pemalang",
            "kode_kec": "032710",
            "kecamatan": "Kec. Petarukan",
            "npsn": 69807730,
            "sekolah": "SPS LESTARI",
            "bentuk": "Unknown",
            "status": "Swasta",
            "sinkron_terakhir": "14 Jan 2024 07:23:03",
            "sekolah_id_enkrip": "496E578E16F73E0C41AD"
        },
        {
            "kode_prop": "030000",
            "propinsi": "Prov. Jawa Tengah",
            "kode_kab_kota": "032700",
            "kabupaten_kota": "Kab. Pemalang",
            "kode_kec": "032710",
            "kecamatan": "Kec. Petarukan",
            "npsn": 69807754,
            "sekolah": "SPS MELATI",
            "bentuk": "Unknown",
            "status": "Swasta",
            "sinkron_terakhir": "19 Aug 2023 21:25:12",
            "sekolah_id_enkrip": "0FB21F5EBB089453F25F"
        },
        {
            "kode_prop": "030000",
            "propinsi": "Prov. Jawa Tengah",
            "kode_kab_kota": "032700",
            "kabupaten_kota": "Kab. Pemalang",
            "kode_kec": "032710",
            "kecamatan": "Kec. Petarukan",
            "npsn": 69807774,
            "sekolah": "SPS TARUNA",
            "bentuk": "Unknown",
            "status": "Swasta",
            "sinkron_terakhir": "03 Feb 2024 21:06:03",
            "sekolah_id_enkrip": "46C1D067D3AE404EC97E"
        },
        {
            "kode_prop": "030000",
            "propinsi": "Prov. Jawa Tengah",
            "kode_kab_kota": "032700",
            "kabupaten_kota": "Kab. Pemalang",
            "kode_kec": "032710",
            "kecamatan": "Kec. Petarukan",
            "npsn": 20324475,
            "sekolah": "SD N 01 ISER",
            "bentuk": "Unknown",
            "status": "Negeri",
            "sinkron_terakhir": "18 Jan 2024 09:13:34",
            "sekolah_id_enkrip": "49B532E3DF56BA55211C"
        },
        {
            "kode_prop": "030000",
            "propinsi": "Prov. Jawa Tengah",
            "kode_kab_kota": "032700",
            "kabupaten_kota": "Kab. Pemalang",
            "kode_kec": "032710",
            "kecamatan": "Kec. Petarukan",
            "npsn": 20324437,
            "sekolah": "SD N 01 KALIRANDU",
            "bentuk": "Unknown",
            "status": "Negeri",
            "sinkron_terakhir": "24 Jan 2024 12:20:44",
            "sekolah_id_enkrip": "2D7C4AAEB38B81080F8B"
        },
        {
            "kode_prop": "030000",
            "propinsi": "Prov. Jawa Tengah",
            "kode_kab_kota": "032700",
            "kabupaten_kota": "Kab. Pemalang",
            "kode_kec": "032710",
            "kecamatan": "Kec. Petarukan",
            "npsn": 20324462,
            "sekolah": "SD N 01 KENDALDOYONG",
            "bentuk": "Unknown",
            "status": "Negeri",
            "sinkron_terakhir": "04 Feb 2024 23:22:11",
            "sekolah_id_enkrip": "00DA2631A7B52795FBDD"
        },
        {
            "kode_prop": "030000",
            "propinsi": "Prov. Jawa Tengah",
            "kode_kab_kota": "032700",
            "kabupaten_kota": "Kab. Pemalang",
            "kode_kec": "032710",
            "kecamatan": "Kec. Petarukan",
            "npsn": 20324434,
            "sekolah": "SD N 01 KENDALSARI",
            "bentuk": "Unknown",
            "status": "Negeri",
            "sinkron_terakhir": "21 Jan 2024 22:13:33",
            "sekolah_id_enkrip": "D283E8E6A18EA49576FF"
        },
        {
            "kode_prop": "030000",
            "propinsi": "Prov. Jawa Tengah",
            "kode_kab_kota": "032700",
            "kabupaten_kota": "Kab. Pemalang",
            "kode_kec": "032710",
            "kecamatan": "Kec. Petarukan",
            "npsn": 20324552,
            "sekolah": "SD N 01 KLAREYAN",
            "bentuk": "Unknown",
            "status": "Negeri",
            "sinkron_terakhir": "01 Feb 2024 13:07:38",
            "sekolah_id_enkrip": "6420691B88FA49A1BAA9"
        },
        {
            "kode_prop": "030000",
            "propinsi": "Prov. Jawa Tengah",
            "kode_kab_kota": "032700",
            "kabupaten_kota": "Kab. Pemalang",
            "kode_kec": "032710",
            "kecamatan": "Kec. Petarukan",
            "npsn": 20324542,
            "sekolah": "SD N 01 LONING",
            "bentuk": "Unknown",
            "status": "Negeri",
            "sinkron_terakhir": "26 Jan 2024 10:36:12",
            "sekolah_id_enkrip": "5E8AB3F3E249B6C6F6E7"
        },
        {
            "kode_prop": "030000",
            "propinsi": "Prov. Jawa Tengah",
            "kode_kab_kota": "032700",
            "kabupaten_kota": "Kab. Pemalang",
            "kode_kec": "032710",
            "kecamatan": "Kec. Petarukan",
            "npsn": 20324519,
            "sekolah": "SD N 01 PANJUNAN",
            "bentuk": "Unknown",
            "status": "Negeri",
            "sinkron_terakhir": "29 Jan 2024 09:39:04",
            "sekolah_id_enkrip": "B5825D793C1F19D2A558"
        },
        {
            "kode_prop": "030000",
            "propinsi": "Prov. Jawa Tengah",
            "kode_kab_kota": "032700",
            "kabupaten_kota": "Kab. Pemalang",
            "kode_kec": "032710",
            "kecamatan": "Kec. Petarukan",
            "npsn": 20324511,
            "sekolah": "SD N 01 PEGUNDAN",
            "bentuk": "Unknown",
            "status": "Negeri",
            "sinkron_terakhir": "06 Feb 2024 11:20:16",
            "sekolah_id_enkrip": "F7D9C178FAC6F47B7A90"
        },
        {
            "kode_prop": "030000",
            "propinsi": "Prov. Jawa Tengah",
            "kode_kab_kota": "032700",
            "kabupaten_kota": "Kab. Pemalang",
            "kode_kec": "032710",
            "kecamatan": "Kec. Petarukan",
            "npsn": 20324534,
            "sekolah": "SD N 01 PESUCEN",
            "bentuk": "Unknown",
            "status": "Negeri",
            "sinkron_terakhir": "19 Jan 2024 09:47:34",
            "sekolah_id_enkrip": "3ECE45666D7774815458"
        },
        {
            "kode_prop": "030000",
            "propinsi": "Prov. Jawa Tengah",
            "kode_kab_kota": "032700",
            "kabupaten_kota": "Kab. Pemalang",
            "kode_kec": "032710",
            "kecamatan": "Kec. Petarukan",
            "npsn": 20324533,
            "sekolah": "SD N 01 PETANJUNGAN",
            "bentuk": "Unknown",
            "status": "Negeri",
            "sinkron_terakhir": "06 Feb 2024 09:23:45",
            "sekolah_id_enkrip": "843605B6C89801B591F2"
        },
        {
            "kode_prop": "030000",
            "propinsi": "Prov. Jawa Tengah",
            "kode_kab_kota": "032700",
            "kabupaten_kota": "Kab. Pemalang",
            "kode_kec": "032710",
            "kecamatan": "Kec. Petarukan",
            "npsn": 20324874,
            "sekolah": "SD N 01 SIRANGKANG",
            "bentuk": "Unknown",
            "status": "Negeri",
            "sinkron_terakhir": "29 Jan 2024 09:08:15",
            "sekolah_id_enkrip": "FEA40FE88EACFB2B7C4D"
        },
        {
            "kode_prop": "030000",
            "propinsi": "Prov. Jawa Tengah",
            "kode_kab_kota": "032700",
            "kabupaten_kota": "Kab. Pemalang",
            "kode_kec": "032710",
            "kecamatan": "Kec. Petarukan",
            "npsn": 20324872,
            "sekolah": "SD N 01 TEGALMLATI",
            "bentuk": "Unknown",
            "status": "Negeri",
            "sinkron_terakhir": "05 Feb 2024 15:20:37",
            "sekolah_id_enkrip": "64A68B2ED9B825250C82"
        },
        {
            "kode_prop": "030000",
            "propinsi": "Prov. Jawa Tengah",
            "kode_kab_kota": "032700",
            "kabupaten_kota": "Kab. Pemalang",
            "kode_kec": "032710",
            "kecamatan": "Kec. Petarukan",
            "npsn": 20324870,
            "sekolah": "SD N 01 TEMUIRENG",
            "bentuk": "Unknown",
            "status": "Negeri",
            "sinkron_terakhir": "03 Feb 2024 15:29:28",
            "sekolah_id_enkrip": "52CF9935FE650896E2CC"
        },
        {
            "kode_prop": "030000",
            "propinsi": "Prov. Jawa Tengah",
            "kode_kab_kota": "032700",
            "kabupaten_kota": "Kab. Pemalang",
            "kode_kec": "032710",
            "kecamatan": "Kec. Petarukan",
            "npsn": 20324842,
            "sekolah": "SD N 01 WIDODAREN",
            "bentuk": "Unknown",
            "status": "Negeri",
            "sinkron_terakhir": "06 Feb 2024 21:22:34",
            "sekolah_id_enkrip": "6F70F81FCB412D515A9E"
        },
        {
            "kode_prop": "030000",
            "propinsi": "Prov. Jawa Tengah",
            "kode_kab_kota": "032700",
            "kabupaten_kota": "Kab. Pemalang",
            "kode_kec": "032710",
            "kecamatan": "Kec. Petarukan",
            "npsn": 20324955,
            "sekolah": "SD N 02 BULU",
            "bentuk": "Unknown",
            "status": "Negeri",
            "sinkron_terakhir": "30 Jan 2024 20:08:40",
            "sekolah_id_enkrip": "EE94A8879D9BFDCD8AF4"
        },
        {
            "kode_prop": "030000",
            "propinsi": "Prov. Jawa Tengah",
            "kode_kab_kota": "032700",
            "kabupaten_kota": "Kab. Pemalang",
            "kode_kec": "032710",
            "kecamatan": "Kec. Petarukan",
            "npsn": 20324931,
            "sekolah": "SD N 02 ISER",
            "bentuk": "Unknown",
            "status": "Negeri",
            "sinkron_terakhir": "15 Jan 2024 08:17:27",
            "sekolah_id_enkrip": "2BE865E4D096129BF3D6"
        },
        {
            "kode_prop": "030000",
            "propinsi": "Prov. Jawa Tengah",
            "kode_kab_kota": "032700",
            "kabupaten_kota": "Kab. Pemalang",
            "kode_kec": "032710",
            "kecamatan": "Kec. Petarukan",
            "npsn": 20324905,
            "sekolah": "SD N 02 KALIRANDU",
            "bentuk": "Unknown",
            "status": "Negeri",
            "sinkron_terakhir": "24 Jan 2024 23:31:23",
            "sekolah_id_enkrip": "5F173A3FE26056DB0EC4"
        },
        {
            "kode_prop": "030000",
            "propinsi": "Prov. Jawa Tengah",
            "kode_kab_kota": "032700",
            "kabupaten_kota": "Kab. Pemalang",
            "kode_kec": "032710",
            "kecamatan": "Kec. Petarukan",
            "npsn": 20324755,
            "sekolah": "SD N 02 KARANGASEM",
            "bentuk": "Unknown",
            "status": "Negeri",
            "sinkron_terakhir": "19 Jan 2024 09:34:04",
            "sekolah_id_enkrip": "FE7203E00617B639B27F"
        },
        {
            "kode_prop": "030000",
            "propinsi": "Prov. Jawa Tengah",
            "kode_kab_kota": "032700",
            "kabupaten_kota": "Kab. Pemalang",
            "kode_kec": "032710",
            "kecamatan": "Kec. Petarukan",
            "npsn": 20324759,
            "sekolah": "SD N 02 KENDALDOYONG",
            "bentuk": "Unknown",
            "status": "Negeri",
            "sinkron_terakhir": "30 Jan 2024 10:07:43",
            "sekolah_id_enkrip": "8C33A5B1038584F122A7"
        },
        {
            "kode_prop": "030000",
            "propinsi": "Prov. Jawa Tengah",
            "kode_kab_kota": "032700",
            "kabupaten_kota": "Kab. Pemalang",
            "kode_kec": "032710",
            "kecamatan": "Kec. Petarukan",
            "npsn": 20324772,
            "sekolah": "SD N 02 KENDALSARI",
            "bentuk": "Unknown",
            "status": "Negeri",
            "sinkron_terakhir": "29 Jan 2024 13:42:16",
            "sekolah_id_enkrip": "55E4BDEE7E2D9FAFB418"
        },
        {
            "kode_prop": "030000",
            "propinsi": "Prov. Jawa Tengah",
            "kode_kab_kota": "032700",
            "kabupaten_kota": "Kab. Pemalang",
            "kode_kec": "032710",
            "kecamatan": "Kec. Petarukan",
            "npsn": 20324743,
            "sekolah": "SD N 02 LONING",
            "bentuk": "Unknown",
            "status": "Negeri",
            "sinkron_terakhir": "02 Feb 2024 08:29:02",
            "sekolah_id_enkrip": "4C70A8C8732C9B714389"
        },
        {
            "kode_prop": "030000",
            "propinsi": "Prov. Jawa Tengah",
            "kode_kab_kota": "032700",
            "kabupaten_kota": "Kab. Pemalang",
            "kode_kec": "032710",
            "kecamatan": "Kec. Petarukan",
            "npsn": 20341321,
            "sekolah": "SD N 02 PANJUNAN",
            "bentuk": "Unknown",
            "status": "Negeri",
            "sinkron_terakhir": "22 Jan 2024 10:48:41",
            "sekolah_id_enkrip": "5B3F3F450D844C43106C"
        },
        {
            "kode_prop": "030000",
            "propinsi": "Prov. Jawa Tengah",
            "kode_kab_kota": "032700",
            "kabupaten_kota": "Kab. Pemalang",
            "kode_kec": "032710",
            "kecamatan": "Kec. Petarukan",
            "npsn": 20324729,
            "sekolah": "SD N 02 PEGUNDAN",
            "bentuk": "Unknown",
            "status": "Negeri",
            "sinkron_terakhir": "05 Feb 2024 08:54:51",
            "sekolah_id_enkrip": "79A2D87A9DA69FBE87DC"
        },
        {
            "kode_prop": "030000",
            "propinsi": "Prov. Jawa Tengah",
            "kode_kab_kota": "032700",
            "kabupaten_kota": "Kab. Pemalang",
            "kode_kec": "032710",
            "kecamatan": "Kec. Petarukan",
            "npsn": 20324816,
            "sekolah": "SD N 02 PESUCEN",
            "bentuk": "Unknown",
            "status": "Negeri",
            "sinkron_terakhir": "06 Feb 2024 03:53:12",
            "sekolah_id_enkrip": "E5810BEDDAE57BF54E1B"
        },
        {
            "kode_prop": "030000",
            "propinsi": "Prov. Jawa Tengah",
            "kode_kab_kota": "032700",
            "kabupaten_kota": "Kab. Pemalang",
            "kode_kec": "032710",
            "kecamatan": "Kec. Petarukan",
            "npsn": 20324814,
            "sekolah": "SD N 02 PETARUKAN",
            "bentuk": "Unknown",
            "status": "Negeri",
            "sinkron_terakhir": "26 Jan 2024 11:15:21",
            "sekolah_id_enkrip": "8623CB6C03D0BBD8AC62"
        },
        {
            "kode_prop": "030000",
            "propinsi": "Prov. Jawa Tengah",
            "kode_kab_kota": "032700",
            "kabupaten_kota": "Kab. Pemalang",
            "kode_kec": "032710",
            "kecamatan": "Kec. Petarukan",
            "npsn": 20324834,
            "sekolah": "SD N 02 SERANG",
            "bentuk": "Unknown",
            "status": "Negeri",
            "sinkron_terakhir": "30 Jan 2024 22:24:14",
            "sekolah_id_enkrip": "6C2C98AD4F9CA26DBD72"
        },
        {
            "kode_prop": "030000",
            "propinsi": "Prov. Jawa Tengah",
            "kode_kab_kota": "032700",
            "kabupaten_kota": "Kab. Pemalang",
            "kode_kec": "032710",
            "kecamatan": "Kec. Petarukan",
            "npsn": 20324775,
            "sekolah": "SD N 02 TEGALMLATI",
            "bentuk": "Unknown",
            "status": "Negeri",
            "sinkron_terakhir": "18 Jan 2024 09:41:32",
            "sekolah_id_enkrip": "BA4C638F4C502065DE35"
        },
        {
            "kode_prop": "030000",
            "propinsi": "Prov. Jawa Tengah",
            "kode_kab_kota": "032700",
            "kabupaten_kota": "Kab. Pemalang",
            "kode_kec": "032710",
            "kecamatan": "Kec. Petarukan",
            "npsn": 20324791,
            "sekolah": "SD N 02 TEMUIRENG",
            "bentuk": "Unknown",
            "status": "Negeri",
            "sinkron_terakhir": "29 Jan 2024 20:33:06",
            "sekolah_id_enkrip": "D7105A6AD3E2FC0360D0"
        },
        {
            "kode_prop": "030000",
            "propinsi": "Prov. Jawa Tengah",
            "kode_kab_kota": "032700",
            "kabupaten_kota": "Kab. Pemalang",
            "kode_kec": "032710",
            "kecamatan": "Kec. Petarukan",
            "npsn": 20324795,
            "sekolah": "SD N 02 WIDODAREN",
            "bentuk": "Unknown",
            "status": "Negeri",
            "sinkron_terakhir": "31 Dec 2023 11:35:37",
            "sekolah_id_enkrip": "3CE25118BD7F25D4B707"
        },
        {
            "kode_prop": "030000",
            "propinsi": "Prov. Jawa Tengah",
            "kode_kab_kota": "032700",
            "kabupaten_kota": "Kab. Pemalang",
            "kode_kec": "032710",
            "kecamatan": "Kec. Petarukan",
            "npsn": 20324107,
            "sekolah": "SD N 03 BULU",
            "bentuk": "Unknown",
            "status": "Negeri",
            "sinkron_terakhir": "16 Jan 2024 13:59:16",
            "sekolah_id_enkrip": "258C6049CC9D190CC742"
        },
        {
            "kode_prop": "030000",
            "propinsi": "Prov. Jawa Tengah",
            "kode_kab_kota": "032700",
            "kabupaten_kota": "Kab. Pemalang",
            "kode_kec": "032710",
            "kecamatan": "Kec. Petarukan",
            "npsn": 20324052,
            "sekolah": "SD N 03 KALIRANDU",
            "bentuk": "Unknown",
            "status": "Negeri",
            "sinkron_terakhir": "16 Jan 2024 16:12:13",
            "sekolah_id_enkrip": "D3FE17A99F5149FD1D14"
        },
        {
            "kode_prop": "030000",
            "propinsi": "Prov. Jawa Tengah",
            "kode_kab_kota": "032700",
            "kabupaten_kota": "Kab. Pemalang",
            "kode_kec": "032710",
            "kecamatan": "Kec. Petarukan",
            "npsn": 20324049,
            "sekolah": "SD N 03 KARANGASEM",
            "bentuk": "Unknown",
            "status": "Negeri",
            "sinkron_terakhir": "20 Jan 2024 21:02:30",
            "sekolah_id_enkrip": "BC5135AEBD836D669365"
        },
        {
            "kode_prop": "030000",
            "propinsi": "Prov. Jawa Tengah",
            "kode_kab_kota": "032700",
            "kabupaten_kota": "Kab. Pemalang",
            "kode_kec": "032710",
            "kecamatan": "Kec. Petarukan",
            "npsn": 20324070,
            "sekolah": "SD N 03 KENDALDOYONG",
            "bentuk": "Unknown",
            "status": "Negeri",
            "sinkron_terakhir": "20 Jan 2024 00:26:11",
            "sekolah_id_enkrip": "66AE1C4D1DA81DB3EF5C"
        },
        {
            "kode_prop": "030000",
            "propinsi": "Prov. Jawa Tengah",
            "kode_kab_kota": "032700",
            "kabupaten_kota": "Kab. Pemalang",
            "kode_kec": "032710",
            "kecamatan": "Kec. Petarukan",
            "npsn": 20324169,
            "sekolah": "SD N 03 PEGUNDAN",
            "bentuk": "Unknown",
            "status": "Negeri",
            "sinkron_terakhir": "27 Jan 2024 09:42:01",
            "sekolah_id_enkrip": "33BB909701A11783795A"
        },
        {
            "kode_prop": "030000",
            "propinsi": "Prov. Jawa Tengah",
            "kode_kab_kota": "032700",
            "kabupaten_kota": "Kab. Pemalang",
            "kode_kec": "032710",
            "kecamatan": "Kec. Petarukan",
            "npsn": 20324162,
            "sekolah": "SD N 03 PESUCEN",
            "bentuk": "Unknown",
            "status": "Negeri",
            "sinkron_terakhir": "06 Feb 2024 10:06:01",
            "sekolah_id_enkrip": "A2AB135E47A6B3E0BF4E"
        },
        {
            "kode_prop": "030000",
            "propinsi": "Prov. Jawa Tengah",
            "kode_kab_kota": "032700",
            "kabupaten_kota": "Kab. Pemalang",
            "kode_kec": "032710",
            "kecamatan": "Kec. Petarukan",
            "npsn": 20324145,
            "sekolah": "SD N 03 PETANJUNGAN",
            "bentuk": "Unknown",
            "status": "Negeri",
            "sinkron_terakhir": "22 Jan 2024 12:12:57",
            "sekolah_id_enkrip": "352BBEE4F61CC6266BC0"
        },
        {
            "kode_prop": "030000",
            "propinsi": "Prov. Jawa Tengah",
            "kode_kab_kota": "032700",
            "kabupaten_kota": "Kab. Pemalang",
            "kode_kec": "032710",
            "kecamatan": "Kec. Petarukan",
            "npsn": 20324144,
            "sekolah": "SD N 03 PETARUKAN",
            "bentuk": "Unknown",
            "status": "Negeri",
            "sinkron_terakhir": "31 Jan 2024 08:01:59",
            "sekolah_id_enkrip": "A636CE83227DBB3DAA39"
        },
        {
            "kode_prop": "030000",
            "propinsi": "Prov. Jawa Tengah",
            "kode_kab_kota": "032700",
            "kabupaten_kota": "Kab. Pemalang",
            "kode_kec": "032710",
            "kecamatan": "Kec. Petarukan",
            "npsn": 20324115,
            "sekolah": "SD N 03 SERANG",
            "bentuk": "Unknown",
            "status": "Negeri",
            "sinkron_terakhir": "05 Feb 2024 19:46:08",
            "sekolah_id_enkrip": "38EB8B412AF1325227F4"
        },
        {
            "kode_prop": "030000",
            "propinsi": "Prov. Jawa Tengah",
            "kode_kab_kota": "032700",
            "kabupaten_kota": "Kab. Pemalang",
            "kode_kec": "032710",
            "kecamatan": "Kec. Petarukan",
            "npsn": 20324130,
            "sekolah": "SD N 03 TEGALMLATI",
            "bentuk": "Unknown",
            "status": "Negeri",
            "sinkron_terakhir": "24 Jan 2024 11:51:14",
            "sekolah_id_enkrip": "D8E7E21CC55BC9EB2936"
        },
        {
            "kode_prop": "030000",
            "propinsi": "Prov. Jawa Tengah",
            "kode_kab_kota": "032700",
            "kabupaten_kota": "Kab. Pemalang",
            "kode_kec": "032710",
            "kecamatan": "Kec. Petarukan",
            "npsn": 20323956,
            "sekolah": "SD N 03 WIDODAREN",
            "bentuk": "Unknown",
            "status": "Negeri",
            "sinkron_terakhir": "05 Feb 2024 23:53:54",
            "sekolah_id_enkrip": "2BC144B272A3D3723091"
        },
        {
            "kode_prop": "030000",
            "propinsi": "Prov. Jawa Tengah",
            "kode_kab_kota": "032700",
            "kabupaten_kota": "Kab. Pemalang",
            "kode_kec": "032710",
            "kecamatan": "Kec. Petarukan",
            "npsn": 20323972,
            "sekolah": "SD N 04 BULU",
            "bentuk": "Unknown",
            "status": "Negeri",
            "sinkron_terakhir": "05 Feb 2024 23:04:10",
            "sekolah_id_enkrip": "0CCC87323339039010F2"
        },
        {
            "kode_prop": "030000",
            "propinsi": "Prov. Jawa Tengah",
            "kode_kab_kota": "032700",
            "kabupaten_kota": "Kab. Pemalang",
            "kode_kec": "032710",
            "kecamatan": "Kec. Petarukan",
            "npsn": 20323918,
            "sekolah": "SD N 04 KALIRANDU",
            "bentuk": "Unknown",
            "status": "Negeri",
            "sinkron_terakhir": "12 Jan 2024 10:52:46",
            "sekolah_id_enkrip": "2603AB99422FAEC084BB"
        },
        {
            "kode_prop": "030000",
            "propinsi": "Prov. Jawa Tengah",
            "kode_kab_kota": "032700",
            "kabupaten_kota": "Kab. Pemalang",
            "kode_kec": "032710",
            "kecamatan": "Kec. Petarukan",
            "npsn": 20323934,
            "sekolah": "SD N 04 KENDALSARI",
            "bentuk": "Unknown",
            "status": "Negeri",
            "sinkron_terakhir": "23 Jan 2024 09:28:37",
            "sekolah_id_enkrip": "590F0C4DAEF4DD010082"
        },
        {
            "kode_prop": "030000",
            "propinsi": "Prov. Jawa Tengah",
            "kode_kab_kota": "032700",
            "kabupaten_kota": "Kab. Pemalang",
            "kode_kec": "032710",
            "kecamatan": "Kec. Petarukan",
            "npsn": 20323947,
            "sekolah": "SD N 04 KLAREYAN",
            "bentuk": "Unknown",
            "status": "Negeri",
            "sinkron_terakhir": "22 Jan 2024 17:02:39",
            "sekolah_id_enkrip": "BF6B0333402606999AEC"
        },
        {
            "kode_prop": "030000",
            "propinsi": "Prov. Jawa Tengah",
            "kode_kab_kota": "032700",
            "kabupaten_kota": "Kab. Pemalang",
            "kode_kec": "032710",
            "kecamatan": "Kec. Petarukan",
            "npsn": 20323943,
            "sekolah": "SD N 04 LONING",
            "bentuk": "Unknown",
            "status": "Negeri",
            "sinkron_terakhir": "31 Jan 2024 08:40:14",
            "sekolah_id_enkrip": "2BE661BD1A47D563776E"
        },
        {
            "kode_prop": "030000",
            "propinsi": "Prov. Jawa Tengah",
            "kode_kab_kota": "032700",
            "kabupaten_kota": "Kab. Pemalang",
            "kode_kec": "032710",
            "kecamatan": "Kec. Petarukan",
            "npsn": 20324025,
            "sekolah": "SD N 04 PEGUNDAN",
            "bentuk": "Unknown",
            "status": "Negeri",
            "sinkron_terakhir": "26 Jan 2024 10:43:46",
            "sekolah_id_enkrip": "EF09134D8A31E5F1F9C0"
        },
        {
            "kode_prop": "030000",
            "propinsi": "Prov. Jawa Tengah",
            "kode_kab_kota": "032700",
            "kabupaten_kota": "Kab. Pemalang",
            "kode_kec": "032710",
            "kecamatan": "Kec. Petarukan",
            "npsn": 20324021,
            "sekolah": "SD N 04 PESUCEN",
            "bentuk": "Unknown",
            "status": "Negeri",
            "sinkron_terakhir": "05 Feb 2024 09:33:15",
            "sekolah_id_enkrip": "F967D055E9C0B2C4FBA0"
        },
        {
            "kode_prop": "030000",
            "propinsi": "Prov. Jawa Tengah",
            "kode_kab_kota": "032700",
            "kabupaten_kota": "Kab. Pemalang",
            "kode_kec": "032710",
            "kecamatan": "Kec. Petarukan",
            "npsn": 20324020,
            "sekolah": "SD N 04 PETANJUNGAN",
            "bentuk": "Unknown",
            "status": "Negeri",
            "sinkron_terakhir": "05 Feb 2024 11:44:05",
            "sekolah_id_enkrip": "FB7E3D08A00F02DB3C84"
        },
        {
            "kode_prop": "030000",
            "propinsi": "Prov. Jawa Tengah",
            "kode_kab_kota": "032700",
            "kabupaten_kota": "Kab. Pemalang",
            "kode_kec": "032710",
            "kecamatan": "Kec. Petarukan",
            "npsn": 20324019,
            "sekolah": "SD N 04 PETARUKAN",
            "bentuk": "Unknown",
            "status": "Negeri",
            "sinkron_terakhir": "26 Sep 2023 12:20:03",
            "sekolah_id_enkrip": "1FF89C2E8D8CDAF5B02C"
        },
        {
            "kode_prop": "030000",
            "propinsi": "Prov. Jawa Tengah",
            "kode_kab_kota": "032700",
            "kabupaten_kota": "Kab. Pemalang",
            "kode_kec": "032710",
            "kecamatan": "Kec. Petarukan",
            "npsn": 20324044,
            "sekolah": "SD N 04 SERANG",
            "bentuk": "Unknown",
            "status": "Negeri",
            "sinkron_terakhir": "23 Jan 2024 11:52:52",
            "sekolah_id_enkrip": "9E86316152E1890FEA71"
        },
        {
            "kode_prop": "030000",
            "propinsi": "Prov. Jawa Tengah",
            "kode_kab_kota": "032700",
            "kabupaten_kota": "Kab. Pemalang",
            "kode_kec": "032710",
            "kecamatan": "Kec. Petarukan",
            "npsn": 20324015,
            "sekolah": "SD N 04 TEGALMLATI",
            "bentuk": "Unknown",
            "status": "Negeri",
            "sinkron_terakhir": "01 Feb 2024 11:37:46",
            "sekolah_id_enkrip": "E759809E4CE3CBCF9D61"
        },
        {
            "kode_prop": "030000",
            "propinsi": "Prov. Jawa Tengah",
            "kode_kab_kota": "032700",
            "kabupaten_kota": "Kab. Pemalang",
            "kode_kec": "032710",
            "kecamatan": "Kec. Petarukan",
            "npsn": 20323998,
            "sekolah": "SD N 05 KENDALDOYONG",
            "bentuk": "Unknown",
            "status": "Negeri",
            "sinkron_terakhir": "29 Jan 2024 14:00:26",
            "sekolah_id_enkrip": "04363EA52286A7E7317C"
        },
        {
            "kode_prop": "030000",
            "propinsi": "Prov. Jawa Tengah",
            "kode_kab_kota": "032700",
            "kabupaten_kota": "Kab. Pemalang",
            "kode_kec": "032710",
            "kecamatan": "Kec. Petarukan",
            "npsn": 20323981,
            "sekolah": "SD N 05 KENDALSARI",
            "bentuk": "Unknown",
            "status": "Negeri",
            "sinkron_terakhir": "24 Jan 2024 09:34:10",
            "sekolah_id_enkrip": "7CFEAB45F2C51DCCD1F3"
        },
        {
            "kode_prop": "030000",
            "propinsi": "Prov. Jawa Tengah",
            "kode_kab_kota": "032700",
            "kabupaten_kota": "Kab. Pemalang",
            "kode_kec": "032710",
            "kecamatan": "Kec. Petarukan",
            "npsn": 20324351,
            "sekolah": "SD N 05 LONING",
            "bentuk": "Unknown",
            "status": "Negeri",
            "sinkron_terakhir": "01 Feb 2024 16:02:54",
            "sekolah_id_enkrip": "CDBCC15A2A6F1D71B60F"
        },
        {
            "kode_prop": "030000",
            "propinsi": "Prov. Jawa Tengah",
            "kode_kab_kota": "032700",
            "kabupaten_kota": "Kab. Pemalang",
            "kode_kec": "032710",
            "kecamatan": "Kec. Petarukan",
            "npsn": 20324341,
            "sekolah": "SD N 05 PEGUNDAN",
            "bentuk": "Unknown",
            "status": "Negeri",
            "sinkron_terakhir": "30 Jan 2024 11:36:59",
            "sekolah_id_enkrip": "790E02E39E2A8C723B48"
        },
        {
            "kode_prop": "030000",
            "propinsi": "Prov. Jawa Tengah",
            "kode_kab_kota": "032700",
            "kabupaten_kota": "Kab. Pemalang",
            "kode_kec": "032710",
            "kecamatan": "Kec. Petarukan",
            "npsn": 20324353,
            "sekolah": "SD N 05 PETARUKAN",
            "bentuk": "Unknown",
            "status": "Negeri",
            "sinkron_terakhir": "23 Jan 2024 09:54:26",
            "sekolah_id_enkrip": "698B836B444AC3EDD6B4"
        },
        {
            "kode_prop": "030000",
            "propinsi": "Prov. Jawa Tengah",
            "kode_kab_kota": "032700",
            "kabupaten_kota": "Kab. Pemalang",
            "kode_kec": "032710",
            "kecamatan": "Kec. Petarukan",
            "npsn": 20324314,
            "sekolah": "SD N 06 KENDALSARI",
            "bentuk": "Unknown",
            "status": "Negeri",
            "sinkron_terakhir": "06 Feb 2024 01:46:42",
            "sekolah_id_enkrip": "0E6672D9DE3D4B48B3BB"
        },
        {
            "kode_prop": "030000",
            "propinsi": "Prov. Jawa Tengah",
            "kode_kab_kota": "032700",
            "kabupaten_kota": "Kab. Pemalang",
            "kode_kec": "032710",
            "kecamatan": "Kec. Petarukan",
            "npsn": 20324313,
            "sekolah": "SD N 06 LONING",
            "bentuk": "Unknown",
            "status": "Negeri",
            "sinkron_terakhir": "01 Feb 2024 14:09:12",
            "sekolah_id_enkrip": "C0A73F3310641756B257"
        },
        {
            "kode_prop": "030000",
            "propinsi": "Prov. Jawa Tengah",
            "kode_kab_kota": "032700",
            "kabupaten_kota": "Kab. Pemalang",
            "kode_kec": "032710",
            "kecamatan": "Kec. Petarukan",
            "npsn": 20324309,
            "sekolah": "SD N 06 PETARUKAN",
            "bentuk": "Unknown",
            "status": "Negeri",
            "sinkron_terakhir": "05 Feb 2024 08:54:40",
            "sekolah_id_enkrip": "3658EFDD33CA5B50AA12"
        },
        {
            "kode_prop": "030000",
            "propinsi": "Prov. Jawa Tengah",
            "kode_kab_kota": "032700",
            "kabupaten_kota": "Kab. Pemalang",
            "kode_kec": "032710",
            "kecamatan": "Kec. Petarukan",
            "npsn": 20324329,
            "sekolah": "SD N 07 KENDALDOYONG",
            "bentuk": "Unknown",
            "status": "Negeri",
            "sinkron_terakhir": "17 Jan 2024 07:33:38",
            "sekolah_id_enkrip": "32BF5FED9BC8E7E25648"
        },
        {
            "kode_prop": "030000",
            "propinsi": "Prov. Jawa Tengah",
            "kode_kab_kota": "032700",
            "kabupaten_kota": "Kab. Pemalang",
            "kode_kec": "032710",
            "kecamatan": "Kec. Petarukan",
            "npsn": 20324328,
            "sekolah": "SD N 07 KLAREYAN",
            "bentuk": "Unknown",
            "status": "Negeri",
            "sinkron_terakhir": "28 Jan 2024 05:48:48",
            "sekolah_id_enkrip": "500137ED51690960A1AB"
        },
        {
            "kode_prop": "030000",
            "propinsi": "Prov. Jawa Tengah",
            "kode_kab_kota": "032700",
            "kabupaten_kota": "Kab. Pemalang",
            "kode_kec": "032710",
            "kecamatan": "Kec. Petarukan",
            "npsn": 20324408,
            "sekolah": "SD N 08 LONING",
            "bentuk": "Unknown",
            "status": "Negeri",
            "sinkron_terakhir": "06 Feb 2024 14:54:58",
            "sekolah_id_enkrip": "DB400A4F69756D8D3BEB"
        },
        {
            "kode_prop": "030000",
            "propinsi": "Prov. Jawa Tengah",
            "kode_kab_kota": "032700",
            "kabupaten_kota": "Kab. Pemalang",
            "kode_kec": "032710",
            "kecamatan": "Kec. Petarukan",
            "npsn": 20324431,
            "sekolah": "SD N 09 KENDALDOYONG",
            "bentuk": "Unknown",
            "status": "Negeri",
            "sinkron_terakhir": "23 Jan 2024 12:22:59",
            "sekolah_id_enkrip": "26F2E58C8ABBE438870F"
        },
        {
            "kode_prop": "030000",
            "propinsi": "Prov. Jawa Tengah",
            "kode_kab_kota": "032700",
            "kabupaten_kota": "Kab. Pemalang",
            "kode_kec": "032710",
            "kecamatan": "Kec. Petarukan",
            "npsn": 20324384,
            "sekolah": "SD N 09 PETARUKAN",
            "bentuk": "Unknown",
            "status": "Negeri",
            "sinkron_terakhir": "30 Jan 2024 10:54:51",
            "sekolah_id_enkrip": "1D3CCD468D0D8037B451"
        },
        {
            "kode_prop": "030000",
            "propinsi": "Prov. Jawa Tengah",
            "kode_kab_kota": "032700",
            "kabupaten_kota": "Kab. Pemalang",
            "kode_kec": "032710",
            "kecamatan": "Kec. Petarukan",
            "npsn": 20324865,
            "sekolah": "SD N 10 PETARUKAN",
            "bentuk": "Unknown",
            "status": "Negeri",
            "sinkron_terakhir": "05 Feb 2024 09:14:31",
            "sekolah_id_enkrip": "940E8C87C7DD7BF5B463"
        },
        {
            "kode_prop": "030000",
            "propinsi": "Prov. Jawa Tengah",
            "kode_kab_kota": "032700",
            "kabupaten_kota": "Kab. Pemalang",
            "kode_kec": "032710",
            "kecamatan": "Kec. Petarukan",
            "npsn": 20324882,
            "sekolah": "SD NEGERI 01 SERANG",
            "bentuk": "Unknown",
            "status": "Negeri",
            "sinkron_terakhir": "27 Jan 2024 11:35:40",
            "sekolah_id_enkrip": "86FCA6AE558B3A4230B9"
        },
        {
            "kode_prop": "030000",
            "propinsi": "Prov. Jawa Tengah",
            "kode_kab_kota": "032700",
            "kabupaten_kota": "Kab. Pemalang",
            "kode_kec": "032710",
            "kecamatan": "Kec. Petarukan",
            "npsn": 20324827,
            "sekolah": "SD NEGERI 02 SIRANGKANG",
            "bentuk": "Unknown",
            "status": "Negeri",
            "sinkron_terakhir": "29 Jan 2024 09:32:18",
            "sekolah_id_enkrip": "2491CCDD84681EC1EC78"
        },
        {
            "kode_prop": "030000",
            "propinsi": "Prov. Jawa Tengah",
            "kode_kab_kota": "032700",
            "kabupaten_kota": "Kab. Pemalang",
            "kode_kec": "032710",
            "kecamatan": "Kec. Petarukan",
            "npsn": 20324069,
            "sekolah": "SD NEGERI 03 KENDALSARI",
            "bentuk": "Unknown",
            "status": "Negeri",
            "sinkron_terakhir": "18 Jan 2024 10:50:47",
            "sekolah_id_enkrip": "DB7AC0EA5AB2291BD13C"
        },
        {
            "kode_prop": "030000",
            "propinsi": "Prov. Jawa Tengah",
            "kode_kab_kota": "032700",
            "kabupaten_kota": "Kab. Pemalang",
            "kode_kec": "032710",
            "kecamatan": "Kec. Petarukan",
            "npsn": 20324066,
            "sekolah": "SD NEGERI 03 KLAREYAN",
            "bentuk": "Unknown",
            "status": "Negeri",
            "sinkron_terakhir": "01 Feb 2024 10:06:07",
            "sekolah_id_enkrip": "53BC2471D408A82B46C8"
        },
        {
            "kode_prop": "030000",
            "propinsi": "Prov. Jawa Tengah",
            "kode_kab_kota": "032700",
            "kabupaten_kota": "Kab. Pemalang",
            "kode_kec": "032710",
            "kecamatan": "Kec. Petarukan",
            "npsn": 20323933,
            "sekolah": "SD NEGERI 04 KENDALDOYONG",
            "bentuk": "Unknown",
            "status": "Negeri",
            "sinkron_terakhir": "31 Jan 2024 07:47:13",
            "sekolah_id_enkrip": "DAADD12F0E458CFB68EA"
        },
        {
            "kode_prop": "030000",
            "propinsi": "Prov. Jawa Tengah",
            "kode_kab_kota": "032700",
            "kabupaten_kota": "Kab. Pemalang",
            "kode_kec": "032710",
            "kecamatan": "Kec. Petarukan",
            "npsn": 20323994,
            "sekolah": "SD NEGERI 04 TEMUIRENG",
            "bentuk": "Unknown",
            "status": "Negeri",
            "sinkron_terakhir": "06 Feb 2024 15:52:06",
            "sekolah_id_enkrip": "F9BB11DE56B23975F34D"
        },
        {
            "kode_prop": "030000",
            "propinsi": "Prov. Jawa Tengah",
            "kode_kab_kota": "032700",
            "kabupaten_kota": "Kab. Pemalang",
            "kode_kec": "032710",
            "kecamatan": "Kec. Petarukan",
            "npsn": 20324357,
            "sekolah": "SD NEGERI 05 WIDODAREN",
            "bentuk": "Unknown",
            "status": "Negeri",
            "sinkron_terakhir": "23 Jan 2024 20:56:35",
            "sekolah_id_enkrip": "A2F443C72DEDDF68C086"
        },
        {
            "kode_prop": "030000",
            "propinsi": "Prov. Jawa Tengah",
            "kode_kab_kota": "032700",
            "kabupaten_kota": "Kab. Pemalang",
            "kode_kec": "032710",
            "kecamatan": "Kec. Petarukan",
            "npsn": 20324315,
            "sekolah": "SD NEGERI 06 KENDALDOYONG",
            "bentuk": "Unknown",
            "status": "Negeri",
            "sinkron_terakhir": "06 Feb 2024 10:46:55",
            "sekolah_id_enkrip": "5DF3CD528D7D2473EFC8"
        },
        {
            "kode_prop": "030000",
            "propinsi": "Prov. Jawa Tengah",
            "kode_kab_kota": "032700",
            "kabupaten_kota": "Kab. Pemalang",
            "kode_kec": "032710",
            "kecamatan": "Kec. Petarukan",
            "npsn": 20324369,
            "sekolah": "SDN 05 KLAREYAN",
            "bentuk": "Unknown",
            "status": "Negeri",
            "sinkron_terakhir": "30 Jan 2024 07:09:43",
            "sekolah_id_enkrip": "1E77A893403870F391EF"
        },
        {
            "kode_prop": "030000",
            "propinsi": "Prov. Jawa Tengah",
            "kode_kab_kota": "032700",
            "kabupaten_kota": "Kab. Pemalang",
            "kode_kec": "032710",
            "kecamatan": "Kec. Petarukan",
            "npsn": 69993041,
            "sekolah": "SD IT ASYIBYAN PETARUKAN",
            "bentuk": "Unknown",
            "status": "Swasta",
            "sinkron_terakhir": "30 Jan 2024 21:44:11",
            "sekolah_id_enkrip": "B25AC9D2B6E0778DF0EA"
        },
        {
            "kode_prop": "030000",
            "propinsi": "Prov. Jawa Tengah",
            "kode_kab_kota": "032700",
            "kabupaten_kota": "Kab. Pemalang",
            "kode_kec": "032710",
            "kecamatan": "Kec. Petarukan",
            "npsn": 20324655,
            "sekolah": "SD MUH 2 KENDALSARI",
            "bentuk": "Unknown",
            "status": "Swasta",
            "sinkron_terakhir": "30 Jan 2024 21:45:55",
            "sekolah_id_enkrip": "DC9500A960B79B52B31E"
        },
        {
            "kode_prop": "030000",
            "propinsi": "Prov. Jawa Tengah",
            "kode_kab_kota": "032700",
            "kabupaten_kota": "Kab. Pemalang",
            "kode_kec": "032710",
            "kecamatan": "Kec. Petarukan",
            "npsn": 20341327,
            "sekolah": "SD MUH.01 PETARUKAN",
            "bentuk": "Unknown",
            "status": "Swasta",
            "sinkron_terakhir": "16 Jan 2024 11:27:20",
            "sekolah_id_enkrip": "F9A585887F97F0C2A4A9"
        },
        {
            "kode_prop": "030000",
            "propinsi": "Prov. Jawa Tengah",
            "kode_kab_kota": "032700",
            "kabupaten_kota": "Kab. Pemalang",
            "kode_kec": "032710",
            "kecamatan": "Kec. Petarukan",
            "npsn": 20324651,
            "sekolah": "SD Muhammadiyah 03 Panjunan",
            "bentuk": "Unknown",
            "status": "Swasta",
            "sinkron_terakhir": "06 Feb 2024 08:48:33",
            "sekolah_id_enkrip": "1D38646D353FA1EE2D60"
        },
        {
            "kode_prop": "030000",
            "propinsi": "Prov. Jawa Tengah",
            "kode_kab_kota": "032700",
            "kabupaten_kota": "Kab. Pemalang",
            "kode_kec": "032710",
            "kecamatan": "Kec. Petarukan",
            "npsn": 70007898,
            "sekolah": "SDIT DAARUSH SHOBAR KLAREYAN",
            "bentuk": "Unknown",
            "status": "Swasta",
            "sinkron_terakhir": "31 Dec 2023 22:21:26",
            "sekolah_id_enkrip": "7A80102A8003BE7F8735"
        },
        {
            "kode_prop": "030000",
            "propinsi": "Prov. Jawa Tengah",
            "kode_kab_kota": "032700",
            "kabupaten_kota": "Kab. Pemalang",
            "kode_kec": "032710",
            "kecamatan": "Kec. Petarukan",
            "npsn": 69988546,
            "sekolah": "SDIT PERMATA BUNDA",
            "bentuk": "Unknown",
            "status": "Swasta",
            "sinkron_terakhir": "30 Jan 2024 08:23:39",
            "sekolah_id_enkrip": "2FB1D01B1F87B783570C"
        },
        {
            "kode_prop": "030000",
            "propinsi": "Prov. Jawa Tengah",
            "kode_kab_kota": "032700",
            "kabupaten_kota": "Kab. Pemalang",
            "kode_kec": "032710",
            "kecamatan": "Kec. Petarukan",
            "npsn": 20324288,
            "sekolah": "SMP NEGERI 1 PETARUKAN",
            "bentuk": "Unknown",
            "status": "Negeri",
            "sinkron_terakhir": "02 Feb 2024 07:27:32",
            "sekolah_id_enkrip": "3CD5AE8B507A240BFD4A"
        },
        {
            "kode_prop": "030000",
            "propinsi": "Prov. Jawa Tengah",
            "kode_kab_kota": "032700",
            "kabupaten_kota": "Kab. Pemalang",
            "kode_kec": "032710",
            "kecamatan": "Kec. Petarukan",
            "npsn": 20324291,
            "sekolah": "SMP NEGERI 2 PETARUKAN",
            "bentuk": "Unknown",
            "status": "Negeri",
            "sinkron_terakhir": "18 Jan 2024 10:34:42",
            "sekolah_id_enkrip": "81B36644D95910ECDB3A"
        },
        {
            "kode_prop": "030000",
            "propinsi": "Prov. Jawa Tengah",
            "kode_kab_kota": "032700",
            "kabupaten_kota": "Kab. Pemalang",
            "kode_kec": "032710",
            "kecamatan": "Kec. Petarukan",
            "npsn": 20324245,
            "sekolah": "SMP NEGERI 3 PETARUKAN",
            "bentuk": "Unknown",
            "status": "Negeri",
            "sinkron_terakhir": "06 Feb 2024 09:58:32",
            "sekolah_id_enkrip": "FE062695B3D72F160364"
        },
        {
            "kode_prop": "030000",
            "propinsi": "Prov. Jawa Tengah",
            "kode_kab_kota": "032700",
            "kabupaten_kota": "Kab. Pemalang",
            "kode_kec": "032710",
            "kecamatan": "Kec. Petarukan",
            "npsn": 20324268,
            "sekolah": "SMP NEGERI 4 PETARUKAN",
            "bentuk": "Unknown",
            "status": "Negeri",
            "sinkron_terakhir": "02 Feb 2024 08:03:36",
            "sekolah_id_enkrip": "B98A6FC023468236BBC5"
        },
        {
            "kode_prop": "030000",
            "propinsi": "Prov. Jawa Tengah",
            "kode_kab_kota": "032700",
            "kabupaten_kota": "Kab. Pemalang",
            "kode_kec": "032710",
            "kecamatan": "Kec. Petarukan",
            "npsn": 20324263,
            "sekolah": "SMP NEGERI 5 PETARUKAN",
            "bentuk": "Unknown",
            "status": "Negeri",
            "sinkron_terakhir": "05 Feb 2024 11:44:45",
            "sekolah_id_enkrip": "D02D7F816C8E3A7E1EF5"
        },
        {
            "kode_prop": "030000",
            "propinsi": "Prov. Jawa Tengah",
            "kode_kab_kota": "032700",
            "kabupaten_kota": "Kab. Pemalang",
            "kode_kec": "032710",
            "kecamatan": "Kec. Petarukan",
            "npsn": 20341451,
            "sekolah": "SMP NEGERI 6 PETARUKAN",
            "bentuk": "Unknown",
            "status": "Negeri",
            "sinkron_terakhir": "24 Jan 2024 11:32:40",
            "sekolah_id_enkrip": "6316B70BB610F242E46B"
        },
        {
            "kode_prop": "030000",
            "propinsi": "Prov. Jawa Tengah",
            "kode_kab_kota": "032700",
            "kabupaten_kota": "Kab. Pemalang",
            "kode_kec": "032710",
            "kecamatan": "Kec. Petarukan",
            "npsn": 20324183,
            "sekolah": "SMP ISLAM AL KHOIRIYAH",
            "bentuk": "Unknown",
            "status": "Swasta",
            "sinkron_terakhir": "31 Jan 2024 09:35:40",
            "sekolah_id_enkrip": "A9277BC22A818594E75B"
        },
        {
            "kode_prop": "030000",
            "propinsi": "Prov. Jawa Tengah",
            "kode_kab_kota": "032700",
            "kabupaten_kota": "Kab. Pemalang",
            "kode_kec": "032710",
            "kecamatan": "Kec. Petarukan",
            "npsn": 20324202,
            "sekolah": "SMP MUHAMMADIYAH 4 PETARUKAN",
            "bentuk": "Unknown",
            "status": "Swasta",
            "sinkron_terakhir": "15 Dec 2023 23:01:21",
            "sekolah_id_enkrip": "DACEB362C3F489A2F759"
        },
        {
            "kode_prop": "030000",
            "propinsi": "Prov. Jawa Tengah",
            "kode_kab_kota": "032700",
            "kabupaten_kota": "Kab. Pemalang",
            "kode_kec": "032710",
            "kecamatan": "Kec. Petarukan",
            "npsn": 20324190,
            "sekolah": "SMP MUHAMMADIYAH 6 PETARUKAN",
            "bentuk": "Unknown",
            "status": "Swasta",
            "sinkron_terakhir": "25 Jan 2024 08:44:21",
            "sekolah_id_enkrip": "D5F86910B1D431459386"
        },
        {
            "kode_prop": "030000",
            "propinsi": "Prov. Jawa Tengah",
            "kode_kab_kota": "032700",
            "kabupaten_kota": "Kab. Pemalang",
            "kode_kec": "032710",
            "kecamatan": "Kec. Petarukan",
            "npsn": 20324241,
            "sekolah": "SMP MUHAMMADIYAH 9 PETARUKAN",
            "bentuk": "Unknown",
            "status": "Swasta",
            "sinkron_terakhir": "05 Feb 2024 08:50:34",
            "sekolah_id_enkrip": "BE5661CFBA2B166923A1"
        },
        {
            "kode_prop": "030000",
            "propinsi": "Prov. Jawa Tengah",
            "kode_kab_kota": "032700",
            "kabupaten_kota": "Kab. Pemalang",
            "kode_kec": "032710",
            "kecamatan": "Kec. Petarukan",
            "npsn": 20324194,
            "sekolah": "SMP PGRI 5 PETARUKAN",
            "bentuk": "Unknown",
            "status": "Swasta",
            "sinkron_terakhir": "19 Jan 2024 17:13:51",
            "sekolah_id_enkrip": "BB8170084CF93F5CECA6"
        },
        {
            "kode_prop": "030000",
            "propinsi": "Prov. Jawa Tengah",
            "kode_kab_kota": "032700",
            "kabupaten_kota": "Kab. Pemalang",
            "kode_kec": "032710",
            "kecamatan": "Kec. Petarukan",
            "npsn": 20324215,
            "sekolah": "SMAN 1 PETARUKAN",
            "bentuk": "SMA",
            "status": "Negeri",
            "sinkron_terakhir": "06 Feb 2024 14:59:17",
            "sekolah_id_enkrip": "CE76A9D45C923B9BF79D"
        },
        {
            "kode_prop": "030000",
            "propinsi": "Prov. Jawa Tengah",
            "kode_kab_kota": "032700",
            "kabupaten_kota": "Kab. Pemalang",
            "kode_kec": "032710",
            "kecamatan": "Kec. Petarukan",
            "npsn": 20324394,
            "sekolah": "SMAS DIPONEGORO PETARUKAN",
            "bentuk": "SMA",
            "status": "Swasta",
            "sinkron_terakhir": "30 Aug 2022 05:52:34",
            "sekolah_id_enkrip": "618BD65997501EF7271F"
        },
        {
            "kode_prop": "030000",
            "propinsi": "Prov. Jawa Tengah",
            "kode_kab_kota": "032700",
            "kabupaten_kota": "Kab. Pemalang",
            "kode_kec": "032710",
            "kecamatan": "Kec. Petarukan",
            "npsn": 20340638,
            "sekolah": "SMK NEGERI 1 PETARUKAN",
            "bentuk": "SMK",
            "status": "Negeri",
            "sinkron_terakhir": "01 Feb 2024 15:35:27",
            "sekolah_id_enkrip": "EDE211ED9A861D8C752F"
        },
        {
            "kode_prop": "030000",
            "propinsi": "Prov. Jawa Tengah",
            "kode_kab_kota": "032700",
            "kabupaten_kota": "Kab. Pemalang",
            "kode_kec": "032710",
            "kecamatan": "Kec. Petarukan",
            "npsn": 69888722,
            "sekolah": "SMK NU PETARUKAN",
            "bentuk": "SMK",
            "status": "Swasta",
            "sinkron_terakhir": "12 Jan 2024 10:23:39",
            "sekolah_id_enkrip": "3C5787A247F1CBADDC2B"
        },
        {
            "kode_prop": "030000",
            "propinsi": "Prov. Jawa Tengah",
            "kode_kab_kota": "032700",
            "kabupaten_kota": "Kab. Pemalang",
            "kode_kec": "032710",
            "kecamatan": "Kec. Petarukan",
            "npsn": 69775693,
            "sekolah": "SMKS AL MUAWANAH",
            "bentuk": "SMK",
            "status": "Swasta",
            "sinkron_terakhir": "02 Feb 2024 10:24:56",
            "sekolah_id_enkrip": "D405AFBD0CCBFAD00B70"
        },
        {
            "kode_prop": "030000",
            "propinsi": "Prov. Jawa Tengah",
            "kode_kab_kota": "032700",
            "kabupaten_kota": "Kab. Pemalang",
            "kode_kec": "032710",
            "kecamatan": "Kec. Petarukan",
            "npsn": 20324230,
            "sekolah": "SMKS BARUNA PUTRA PETARUKAN",
            "bentuk": "SMK",
            "status": "Swasta",
            "sinkron_terakhir": "06 Feb 2024 21:26:36",
            "sekolah_id_enkrip": "3A5603DC4B82E11FDAEF"
        },
        {
            "kode_prop": "030000",
            "propinsi": "Prov. Jawa Tengah",
            "kode_kab_kota": "032700",
            "kabupaten_kota": "Kab. Pemalang",
            "kode_kec": "032710",
            "kecamatan": "Kec. Petarukan",
            "npsn": 20324231,
            "sekolah": "SMKS ISLAM AL KHOIRIYAH PETARUKAN",
            "bentuk": "SMK",
            "status": "Swasta",
            "sinkron_terakhir": "30 Jan 2024 15:18:55",
            "sekolah_id_enkrip": "FD5DF11830E78FFF5D7D"
        },
        {
            "kode_prop": "030000",
            "propinsi": "Prov. Jawa Tengah",
            "kode_kab_kota": "032700",
            "kabupaten_kota": "Kab. Pemalang",
            "kode_kec": "032710",
            "kecamatan": "Kec. Petarukan",
            "npsn": 20362557,
            "sekolah": "SMKS KESEHATAN MEDIKA FARMA PETARUKAN",
            "bentuk": "SMK",
            "status": "Swasta",
            "sinkron_terakhir": "06 Feb 2024 21:06:47",
            "sekolah_id_enkrip": "A3A99B8F0CB146DFB550"
        },
        {
            "kode_prop": "030000",
            "propinsi": "Prov. Jawa Tengah",
            "kode_kab_kota": "032700",
            "kabupaten_kota": "Kab. Pemalang",
            "kode_kec": "032710",
            "kecamatan": "Kec. Petarukan",
            "npsn": 20340639,
            "sekolah": "SMKS MUHAMMADIYAH 5 PETARUKAN",
            "bentuk": "SMK",
            "status": "Swasta",
            "sinkron_terakhir": "31 Jan 2024 11:16:21",
            "sekolah_id_enkrip": "3605F529A09740401D1F"
        },
        {
            "kode_prop": "030000",
            "propinsi": "Prov. Jawa Tengah",
            "kode_kab_kota": "032700",
            "kabupaten_kota": "Kab. Pemalang",
            "kode_kec": "032710",
            "kecamatan": "Kec. Petarukan",
            "npsn": 20324207,
            "sekolah": "SMKS SATYA PRAJA 1 PETARUKAN",
            "bentuk": "SMK",
            "status": "Swasta",
            "sinkron_terakhir": "05 Feb 2024 13:00:00",
            "sekolah_id_enkrip": "7AD901DAD36799DB7DDB"
        },
        {
            "kode_prop": "030000",
            "propinsi": "Prov. Jawa Tengah",
            "kode_kab_kota": "032700",
            "kabupaten_kota": "Kab. Pemalang",
            "kode_kec": "032710",
            "kecamatan": "Kec. Petarukan",
            "npsn": 20324206,
            "sekolah": "SMKS SATYA PRAJA 2 PETARUKAN",
            "bentuk": "SMK",
            "status": "Swasta",
            "sinkron_terakhir": "05 Feb 2024 11:07:58",
            "sekolah_id_enkrip": "FB1A8A1F63A55D287616"
        },
        {
            "kode_prop": "030000",
            "propinsi": "Prov. Jawa Tengah",
            "kode_kab_kota": "032700",
            "kabupaten_kota": "Kab. Pemalang",
            "kode_kec": "032710",
            "kecamatan": "Kec. Petarukan",
            "npsn": "P9948640",
            "sekolah": "PKBM TARUNA",
            "bentuk": "PKBM",
            "status": "Swasta",
            "sinkron_terakhir": "05 Feb 2024 14:06:58",
            "sekolah_id_enkrip": "8441F691320F6C749C1A"
        }
    ]
}