{
    "260900": [
        {
            "kode_prop": "260000",
            "propinsi": "Prov. Bengkulu",
            "kode_kab_kota": "260900",
            "kabupaten_kota": "Kab. Bengkulu Tengah",
            "kode_kec": "260901",
            "kecamatan": "Kec. Talang Empat",
            "npsn": 69909765,
            "sekolah": "TK NEGERI DHARMA WANITA",
            "bentuk": "Unknown",
            "status": "Negeri",
            "sinkron_terakhir": "22 Aug 2023 06:43:06",
            "sekolah_id_enkrip": "4399A764C6C8B09E5D6C"
        },
        {
            "kode_prop": "260000",
            "propinsi": "Prov. Bengkulu",
            "kode_kab_kota": "260900",
            "kabupaten_kota": "Kab. Bengkulu Tengah",
            "kode_kec": "260901",
            "kecamatan": "Kec. Talang Empat",
            "npsn": 69863862,
            "sekolah": "TK NEGERI SAYANG BUNDA",
            "bentuk": "Unknown",
            "status": "Negeri",
            "sinkron_terakhir": "01 Dec 2023 11:23:35",
            "sekolah_id_enkrip": "0828D2315970776A4C78"
        },
        {
            "kode_prop": "260000",
            "propinsi": "Prov. Bengkulu",
            "kode_kab_kota": "260900",
            "kabupaten_kota": "Kab. Bengkulu Tengah",
            "kode_kec": "260901",
            "kecamatan": "Kec. Talang Empat",
            "npsn": 69863861,
            "sekolah": "TK ISLAMIC CENTRE",
            "bentuk": "Unknown",
            "status": "Swasta",
            "sinkron_terakhir": "10 Jun 2023 22:16:21",
            "sekolah_id_enkrip": "1CDC2AEA19F6A4055C39"
        },
        {
            "kode_prop": "260000",
            "propinsi": "Prov. Bengkulu",
            "kode_kab_kota": "260900",
            "kabupaten_kota": "Kab. Bengkulu Tengah",
            "kode_kec": "260901",
            "kecamatan": "Kec. Talang Empat",
            "npsn": 69987020,
            "sekolah": "TK IT AL-HUDA",
            "bentuk": "Unknown",
            "status": "Swasta",
            "sinkron_terakhir": "27 Dec 2023 11:40:39",
            "sekolah_id_enkrip": "2CB4E157BAAA20C35E4F"
        },
        {
            "kode_prop": "260000",
            "propinsi": "Prov. Bengkulu",
            "kode_kab_kota": "260900",
            "kabupaten_kota": "Kab. Bengkulu Tengah",
            "kode_kec": "260901",
            "kecamatan": "Kec. Talang Empat",
            "npsn": 10703556,
            "sekolah": "TK MAWAR",
            "bentuk": "Unknown",
            "status": "Swasta",
            "sinkron_terakhir": "01 Feb 2024 12:02:08",
            "sekolah_id_enkrip": "3B1F9DCC201BFD3657FB"
        },
        {
            "kode_prop": "260000",
            "propinsi": "Prov. Bengkulu",
            "kode_kab_kota": "260900",
            "kabupaten_kota": "Kab. Bengkulu Tengah",
            "kode_kec": "260901",
            "kecamatan": "Kec. Talang Empat",
            "npsn": 69863845,
            "sekolah": "TK PATI KEDATON",
            "bentuk": "Unknown",
            "status": "Swasta",
            "sinkron_terakhir": "25 Jan 2024 09:21:41",
            "sekolah_id_enkrip": "27F6DBF74F2846D99DC3"
        },
        {
            "kode_prop": "260000",
            "propinsi": "Prov. Bengkulu",
            "kode_kab_kota": "260900",
            "kabupaten_kota": "Kab. Bengkulu Tengah",
            "kode_kec": "260901",
            "kecamatan": "Kec. Talang Empat",
            "npsn": 69909772,
            "sekolah": "TK SATU ATAP TENGAH PADANG",
            "bentuk": "Unknown",
            "status": "Swasta",
            "sinkron_terakhir": "13 Jan 2024 22:10:55",
            "sekolah_id_enkrip": "5D86D507A2F3C72A651B"
        },
        {
            "kode_prop": "260000",
            "propinsi": "Prov. Bengkulu",
            "kode_kab_kota": "260900",
            "kabupaten_kota": "Kab. Bengkulu Tengah",
            "kode_kec": "260901",
            "kecamatan": "Kec. Talang Empat",
            "npsn": 69863851,
            "sekolah": "KB A-SYIFA",
            "bentuk": "Unknown",
            "status": "Swasta",
            "sinkron_terakhir": "18 Aug 2023 22:45:39",
            "sekolah_id_enkrip": "3987996322AFED08A529"
        },
        {
            "kode_prop": "260000",
            "propinsi": "Prov. Bengkulu",
            "kode_kab_kota": "260900",
            "kabupaten_kota": "Kab. Bengkulu Tengah",
            "kode_kec": "260901",
            "kecamatan": "Kec. Talang Empat",
            "npsn": 69863858,
            "sekolah": "KB BINA INSAN",
            "bentuk": "Unknown",
            "status": "Swasta",
            "sinkron_terakhir": "30 Jul 2023 15:21:57",
            "sekolah_id_enkrip": "16A41F0F7709E2C90D2D"
        },
        {
            "kode_prop": "260000",
            "propinsi": "Prov. Bengkulu",
            "kode_kab_kota": "260900",
            "kabupaten_kota": "Kab. Bengkulu Tengah",
            "kode_kec": "260901",
            "kecamatan": "Kec. Talang Empat",
            "npsn": 69863853,
            "sekolah": "KB CINTA BUNDA",
            "bentuk": "Unknown",
            "status": "Swasta",
            "sinkron_terakhir": "21 Aug 2023 14:05:36",
            "sekolah_id_enkrip": "852DC665D44626A8ACB3"
        },
        {
            "kode_prop": "260000",
            "propinsi": "Prov. Bengkulu",
            "kode_kab_kota": "260900",
            "kabupaten_kota": "Kab. Bengkulu Tengah",
            "kode_kec": "260901",
            "kecamatan": "Kec. Talang Empat",
            "npsn": 69863867,
            "sekolah": "KB IBU PERTIWI",
            "bentuk": "Unknown",
            "status": "Swasta",
            "sinkron_terakhir": "02 Nov 2023 21:34:58",
            "sekolah_id_enkrip": "DF9795E04CAF456AB0FF"
        },
        {
            "kode_prop": "260000",
            "propinsi": "Prov. Bengkulu",
            "kode_kab_kota": "260900",
            "kabupaten_kota": "Kab. Bengkulu Tengah",
            "kode_kec": "260901",
            "kecamatan": "Kec. Talang Empat",
            "npsn": 69863868,
            "sekolah": "KB KASIH IBU",
            "bentuk": "Unknown",
            "status": "Swasta",
            "sinkron_terakhir": "17 Aug 2023 22:13:29",
            "sekolah_id_enkrip": "24C25B70B2C4731CAE2B"
        },
        {
            "kode_prop": "260000",
            "propinsi": "Prov. Bengkulu",
            "kode_kab_kota": "260900",
            "kabupaten_kota": "Kab. Bengkulu Tengah",
            "kode_kec": "260901",
            "kecamatan": "Kec. Talang Empat",
            "npsn": 69863855,
            "sekolah": "KB KHINANTI",
            "bentuk": "Unknown",
            "status": "Swasta",
            "sinkron_terakhir": "29 Aug 2023 20:55:17",
            "sekolah_id_enkrip": "DD265D1259DBAA1FE863"
        },
        {
            "kode_prop": "260000",
            "propinsi": "Prov. Bengkulu",
            "kode_kab_kota": "260900",
            "kabupaten_kota": "Kab. Bengkulu Tengah",
            "kode_kec": "260901",
            "kecamatan": "Kec. Talang Empat",
            "npsn": 69863857,
            "sekolah": "KB MARISA",
            "bentuk": "Unknown",
            "status": "Swasta",
            "sinkron_terakhir": "30 Aug 2023 18:12:46",
            "sekolah_id_enkrip": "6BFC0FC0D4C476F41DBD"
        },
        {
            "kode_prop": "260000",
            "propinsi": "Prov. Bengkulu",
            "kode_kab_kota": "260900",
            "kabupaten_kota": "Kab. Bengkulu Tengah",
            "kode_kec": "260901",
            "kecamatan": "Kec. Talang Empat",
            "npsn": 69863869,
            "sekolah": "KB MUTIARA BUNDA",
            "bentuk": "Unknown",
            "status": "Swasta",
            "sinkron_terakhir": "17 Oct 2023 09:12:41",
            "sekolah_id_enkrip": "BB96A9912AAA87E7F601"
        },
        {
            "kode_prop": "260000",
            "propinsi": "Prov. Bengkulu",
            "kode_kab_kota": "260900",
            "kabupaten_kota": "Kab. Bengkulu Tengah",
            "kode_kec": "260901",
            "kecamatan": "Kec. Talang Empat",
            "npsn": 69863866,
            "sekolah": "KB TUNAS CENDIKIA",
            "bentuk": "Unknown",
            "status": "Swasta",
            "sinkron_terakhir": "14 Oct 2023 16:57:37",
            "sekolah_id_enkrip": "FE341F7A36214B79F41E"
        },
        {
            "kode_prop": "260000",
            "propinsi": "Prov. Bengkulu",
            "kode_kab_kota": "260900",
            "kabupaten_kota": "Kab. Bengkulu Tengah",
            "kode_kec": "260901",
            "kecamatan": "Kec. Talang Empat",
            "npsn": 69909780,
            "sekolah": "PAUD BUKIT INDAH LESTARI",
            "bentuk": "Unknown",
            "status": "Swasta",
            "sinkron_terakhir": "26 Jan 2024 11:12:29",
            "sekolah_id_enkrip": "E7BF874E76169FB41864"
        },
        {
            "kode_prop": "260000",
            "propinsi": "Prov. Bengkulu",
            "kode_kab_kota": "260900",
            "kabupaten_kota": "Kab. Bengkulu Tengah",
            "kode_kec": "260901",
            "kecamatan": "Kec. Talang Empat",
            "npsn": 69939963,
            "sekolah": "PAUD CINTA KASIH AYAH",
            "bentuk": "Unknown",
            "status": "Swasta",
            "sinkron_terakhir": "30 Sep 2023 09:28:49",
            "sekolah_id_enkrip": "FE2FA5F046C33DAD649E"
        },
        {
            "kode_prop": "260000",
            "propinsi": "Prov. Bengkulu",
            "kode_kab_kota": "260900",
            "kabupaten_kota": "Kab. Bengkulu Tengah",
            "kode_kec": "260901",
            "kecamatan": "Kec. Talang Empat",
            "npsn": 69831800,
            "sekolah": "TABA CERIA",
            "bentuk": "Unknown",
            "status": "Swasta",
            "sinkron_terakhir": "21 Aug 2023 22:53:12",
            "sekolah_id_enkrip": "E67C1F677031BD0CBBA0"
        },
        {
            "kode_prop": "260000",
            "propinsi": "Prov. Bengkulu",
            "kode_kab_kota": "260900",
            "kabupaten_kota": "Kab. Bengkulu Tengah",
            "kode_kec": "260901",
            "kecamatan": "Kec. Talang Empat",
            "npsn": 69961800,
            "sekolah": "TPA A-SYIFA",
            "bentuk": "Unknown",
            "status": "Swasta",
            "sinkron_terakhir": "03 Feb 2024 17:05:52",
            "sekolah_id_enkrip": "AE6876E24C04DED372D7"
        },
        {
            "kode_prop": "260000",
            "propinsi": "Prov. Bengkulu",
            "kode_kab_kota": "260900",
            "kabupaten_kota": "Kab. Bengkulu Tengah",
            "kode_kec": "260901",
            "kecamatan": "Kec. Talang Empat",
            "npsn": 10700493,
            "sekolah": "SD NEGERI 01 BENGKULU TENGAH",
            "bentuk": "Unknown",
            "status": "Negeri",
            "sinkron_terakhir": "02 Feb 2024 20:09:20",
            "sekolah_id_enkrip": "D6FBFC2FC481B3100FF8"
        },
        {
            "kode_prop": "260000",
            "propinsi": "Prov. Bengkulu",
            "kode_kab_kota": "260900",
            "kabupaten_kota": "Kab. Bengkulu Tengah",
            "kode_kec": "260901",
            "kecamatan": "Kec. Talang Empat",
            "npsn": 10700347,
            "sekolah": "SD NEGERI 05 BENGKULU TENGAH",
            "bentuk": "Unknown",
            "status": "Negeri",
            "sinkron_terakhir": "05 Feb 2024 10:04:37",
            "sekolah_id_enkrip": "B6D6725EACC9DA17B827"
        },
        {
            "kode_prop": "260000",
            "propinsi": "Prov. Bengkulu",
            "kode_kab_kota": "260900",
            "kabupaten_kota": "Kab. Bengkulu Tengah",
            "kode_kec": "260901",
            "kecamatan": "Kec. Talang Empat",
            "npsn": 10700110,
            "sekolah": "SD NEGERI 15 BENGKULU TENGAH",
            "bentuk": "Unknown",
            "status": "Negeri",
            "sinkron_terakhir": "06 Feb 2024 11:35:04",
            "sekolah_id_enkrip": "8651E976D8AD1240BE28"
        },
        {
            "kode_prop": "260000",
            "propinsi": "Prov. Bengkulu",
            "kode_kab_kota": "260900",
            "kabupaten_kota": "Kab. Bengkulu Tengah",
            "kode_kec": "260901",
            "kecamatan": "Kec. Talang Empat",
            "npsn": 10700157,
            "sekolah": "SD NEGERI 27 BENGKULU TENGAH",
            "bentuk": "Unknown",
            "status": "Negeri",
            "sinkron_terakhir": "31 Jan 2024 11:11:11",
            "sekolah_id_enkrip": "231A914FF75CAB53B1F2"
        },
        {
            "kode_prop": "260000",
            "propinsi": "Prov. Bengkulu",
            "kode_kab_kota": "260900",
            "kabupaten_kota": "Kab. Bengkulu Tengah",
            "kode_kec": "260901",
            "kecamatan": "Kec. Talang Empat",
            "npsn": 10700152,
            "sekolah": "SD NEGERI 59 BENGKULU TENGAH",
            "bentuk": "Unknown",
            "status": "Negeri",
            "sinkron_terakhir": "05 Feb 2024 10:02:48",
            "sekolah_id_enkrip": "F2DE60D6883F7AFF26DF"
        },
        {
            "kode_prop": "260000",
            "propinsi": "Prov. Bengkulu",
            "kode_kab_kota": "260900",
            "kabupaten_kota": "Kab. Bengkulu Tengah",
            "kode_kec": "260901",
            "kecamatan": "Kec. Talang Empat",
            "npsn": 10700460,
            "sekolah": "SD NEGERI 68 BENGKULU TENGAH",
            "bentuk": "Unknown",
            "status": "Negeri",
            "sinkron_terakhir": "01 Feb 2024 19:28:54",
            "sekolah_id_enkrip": "EA23A963753529C3469A"
        },
        {
            "kode_prop": "260000",
            "propinsi": "Prov. Bengkulu",
            "kode_kab_kota": "260900",
            "kabupaten_kota": "Kab. Bengkulu Tengah",
            "kode_kec": "260901",
            "kecamatan": "Kec. Talang Empat",
            "npsn": 10700429,
            "sekolah": "SD NEGERI 79 BENGKULU TENGAH",
            "bentuk": "Unknown",
            "status": "Negeri",
            "sinkron_terakhir": "03 Feb 2024 12:04:14",
            "sekolah_id_enkrip": "2FAFF2843A081EF49522"
        },
        {
            "kode_prop": "260000",
            "propinsi": "Prov. Bengkulu",
            "kode_kab_kota": "260900",
            "kabupaten_kota": "Kab. Bengkulu Tengah",
            "kode_kec": "260901",
            "kecamatan": "Kec. Talang Empat",
            "npsn": 70036790,
            "sekolah": "SD IHYAUL QURAN",
            "bentuk": "Unknown",
            "status": "Swasta",
            "sinkron_terakhir": "04 Sep 2023 10:28:53",
            "sekolah_id_enkrip": "E31C74A84C53D7F71226"
        },
        {
            "kode_prop": "260000",
            "propinsi": "Prov. Bengkulu",
            "kode_kab_kota": "260900",
            "kabupaten_kota": "Kab. Bengkulu Tengah",
            "kode_kec": "260901",
            "kecamatan": "Kec. Talang Empat",
            "npsn": 10700232,
            "sekolah": "SMP NEGERI 03 BENGKULU TENGAH",
            "bentuk": "Unknown",
            "status": "Negeri",
            "sinkron_terakhir": "06 Feb 2024 08:54:17",
            "sekolah_id_enkrip": "F19F7E240D1741A1947F"
        },
        {
            "kode_prop": "260000",
            "propinsi": "Prov. Bengkulu",
            "kode_kab_kota": "260900",
            "kabupaten_kota": "Kab. Bengkulu Tengah",
            "kode_kec": "260901",
            "kecamatan": "Kec. Talang Empat",
            "npsn": 10700254,
            "sekolah": "SMP NEGERI 06 BENGKULU TENGAH",
            "bentuk": "Unknown",
            "status": "Negeri",
            "sinkron_terakhir": "30 Jan 2024 10:25:44",
            "sekolah_id_enkrip": "D1BBCAA28AF6AC98A4AA"
        },
        {
            "kode_prop": "260000",
            "propinsi": "Prov. Bengkulu",
            "kode_kab_kota": "260900",
            "kabupaten_kota": "Kab. Bengkulu Tengah",
            "kode_kec": "260901",
            "kecamatan": "Kec. Talang Empat",
            "npsn": 10702857,
            "sekolah": "SMP NEGERI 11 BENGKULU TENGAH",
            "bentuk": "Unknown",
            "status": "Negeri",
            "sinkron_terakhir": "25 Jan 2024 11:43:41",
            "sekolah_id_enkrip": "2B86984225E801667D06"
        },
        {
            "kode_prop": "260000",
            "propinsi": "Prov. Bengkulu",
            "kode_kab_kota": "260900",
            "kabupaten_kota": "Kab. Bengkulu Tengah",
            "kode_kec": "260901",
            "kecamatan": "Kec. Talang Empat",
            "npsn": 10703589,
            "sekolah": "SMP NEGERI 26 BENGKULU TENGAH",
            "bentuk": "Unknown",
            "status": "Negeri",
            "sinkron_terakhir": "02 Feb 2024 09:19:45",
            "sekolah_id_enkrip": "EB65902C67CBC084AC5D"
        },
        {
            "kode_prop": "260000",
            "propinsi": "Prov. Bengkulu",
            "kode_kab_kota": "260900",
            "kabupaten_kota": "Kab. Bengkulu Tengah",
            "kode_kec": "260901",
            "kecamatan": "Kec. Talang Empat",
            "npsn": 70005529,
            "sekolah": "SMP IHYAUL QURAN",
            "bentuk": "Unknown",
            "status": "Swasta",
            "sinkron_terakhir": "03 Feb 2024 14:41:20",
            "sekolah_id_enkrip": "A5DB5A8009FD639AFA78"
        },
        {
            "kode_prop": "260000",
            "propinsi": "Prov. Bengkulu",
            "kode_kab_kota": "260900",
            "kabupaten_kota": "Kab. Bengkulu Tengah",
            "kode_kec": "260901",
            "kecamatan": "Kec. Talang Empat",
            "npsn": 10700303,
            "sekolah": "SMAN 1 BENGKULU TENGAH",
            "bentuk": "SMA",
            "status": "Negeri",
            "sinkron_terakhir": "06 Feb 2024 11:54:31",
            "sekolah_id_enkrip": "0CF1EDAA8377418F0ABD"
        },
        {
            "kode_prop": "260000",
            "propinsi": "Prov. Bengkulu",
            "kode_kab_kota": "260900",
            "kabupaten_kota": "Kab. Bengkulu Tengah",
            "kode_kec": "260901",
            "kecamatan": "Kec. Talang Empat",
            "npsn": 69734272,
            "sekolah": "SMAN 6 BENGKULU TENGAH",
            "bentuk": "SMA",
            "status": "Negeri",
            "sinkron_terakhir": "05 Feb 2024 11:30:41",
            "sekolah_id_enkrip": "178BFE78F547FF4289A9"
        },
        {
            "kode_prop": "260000",
            "propinsi": "Prov. Bengkulu",
            "kode_kab_kota": "260900",
            "kabupaten_kota": "Kab. Bengkulu Tengah",
            "kode_kec": "260901",
            "kecamatan": "Kec. Talang Empat",
            "npsn": 69992905,
            "sekolah": "SMA Ihyaul Quran",
            "bentuk": "SMA",
            "status": "Swasta",
            "sinkron_terakhir": "29 Jan 2024 10:16:47",
            "sekolah_id_enkrip": "7BBC12C68C9A02A997CD"
        },
        {
            "kode_prop": "260000",
            "propinsi": "Prov. Bengkulu",
            "kode_kab_kota": "260900",
            "kabupaten_kota": "Kab. Bengkulu Tengah",
            "kode_kec": "260901",
            "kecamatan": "Kec. Talang Empat",
            "npsn": "P9934544",
            "sekolah": "PKBM KHINANTI",
            "bentuk": "PKBM",
            "status": "Swasta",
            "sinkron_terakhir": "16 Jan 2024 11:22:13",
            "sekolah_id_enkrip": "AAD06212D4DA29E77C4E"
        },
        {
            "kode_prop": "260000",
            "propinsi": "Prov. Bengkulu",
            "kode_kab_kota": "260900",
            "kabupaten_kota": "Kab. Bengkulu Tengah",
            "kode_kec": "260901",
            "kecamatan": "Kec. Talang Empat",
            "npsn": 69725942,
            "sekolah": "SLBN 1 BENGKULU TENGAH",
            "bentuk": "Unknown",
            "status": "Negeri",
            "sinkron_terakhir": "30 Jan 2024 21:36:10",
            "sekolah_id_enkrip": "E0FF589C532253DB8A15"
        }
    ]
}