{
    "286000": [
        {
            "kode_prop": "280000",
            "propinsi": "Prov. Banten",
            "kode_kab_kota": "286000",
            "kabupaten_kota": "Kota Cilegon",
            "kode_kec": "286006",
            "kecamatan": "Kec. Purwakarta",
            "npsn": 69772849,
            "sekolah": "TK NEGERI KENANGA",
            "bentuk": "Unknown",
            "status": "Negeri",
            "sinkron_terakhir": "23 Jan 2024 12:24:25",
            "sekolah_id_enkrip": "FFAE9EADAE8D76CA250E"
        },
        {
            "kode_prop": "280000",
            "propinsi": "Prov. Banten",
            "kode_kab_kota": "286000",
            "kabupaten_kota": "Kota Cilegon",
            "kode_kec": "286006",
            "kecamatan": "Kec. Purwakarta",
            "npsn": 20614688,
            "sekolah": "TK NEGERI PECINAN",
            "bentuk": "Unknown",
            "status": "Negeri",
            "sinkron_terakhir": "22 Jan 2024 18:02:08",
            "sekolah_id_enkrip": "254D16B1A6B0EBFC2693"
        },
        {
            "kode_prop": "280000",
            "propinsi": "Prov. Banten",
            "kode_kab_kota": "286000",
            "kabupaten_kota": "Kota Cilegon",
            "kode_kec": "286006",
            "kecamatan": "Kec. Purwakarta",
            "npsn": 20614681,
            "sekolah": "TK AL - KHAERIYAH KEB DLM",
            "bentuk": "Unknown",
            "status": "Swasta",
            "sinkron_terakhir": "19 Jan 2024 10:40:57",
            "sekolah_id_enkrip": "77407F75E2392D7A7865"
        },
        {
            "kode_prop": "280000",
            "propinsi": "Prov. Banten",
            "kode_kab_kota": "286000",
            "kabupaten_kota": "Kota Cilegon",
            "kode_kec": "286006",
            "kecamatan": "Kec. Purwakarta",
            "npsn": 20614683,
            "sekolah": "TK AL FURQOON",
            "bentuk": "Unknown",
            "status": "Swasta",
            "sinkron_terakhir": "30 Jan 2024 22:50:19",
            "sekolah_id_enkrip": "D475C743DA94E6E46A07"
        },
        {
            "kode_prop": "280000",
            "propinsi": "Prov. Banten",
            "kode_kab_kota": "286000",
            "kabupaten_kota": "Kota Cilegon",
            "kode_kec": "286006",
            "kecamatan": "Kec. Purwakarta",
            "npsn": 20614687,
            "sekolah": "TK AL-MUHAJIRIN",
            "bentuk": "Unknown",
            "status": "Swasta",
            "sinkron_terakhir": "17 Jan 2024 15:42:36",
            "sekolah_id_enkrip": "6EFFD4DD809F63202BC0"
        },
        {
            "kode_prop": "280000",
            "propinsi": "Prov. Banten",
            "kode_kab_kota": "286000",
            "kabupaten_kota": "Kota Cilegon",
            "kode_kec": "286006",
            "kecamatan": "Kec. Purwakarta",
            "npsn": 20614686,
            "sekolah": "TK AN-NAJAT",
            "bentuk": "Unknown",
            "status": "Swasta",
            "sinkron_terakhir": "26 Jan 2024 09:41:01",
            "sekolah_id_enkrip": "FD8C22B0EB82A9C02F78"
        },
        {
            "kode_prop": "280000",
            "propinsi": "Prov. Banten",
            "kode_kab_kota": "286000",
            "kabupaten_kota": "Kota Cilegon",
            "kode_kec": "286006",
            "kecamatan": "Kec. Purwakarta",
            "npsn": 20614685,
            "sekolah": "TK BINA BUDI I",
            "bentuk": "Unknown",
            "status": "Swasta",
            "sinkron_terakhir": "17 Jan 2024 11:28:59",
            "sekolah_id_enkrip": "8559488E4F74406C2D1D"
        },
        {
            "kode_prop": "280000",
            "propinsi": "Prov. Banten",
            "kode_kab_kota": "286000",
            "kabupaten_kota": "Kota Cilegon",
            "kode_kec": "286006",
            "kecamatan": "Kec. Purwakarta",
            "npsn": 20614689,
            "sekolah": "TK IT AL - MUQORROBIN",
            "bentuk": "Unknown",
            "status": "Swasta",
            "sinkron_terakhir": "12 Jan 2024 12:19:05",
            "sekolah_id_enkrip": "307D5EA0C951A4BA7496"
        },
        {
            "kode_prop": "280000",
            "propinsi": "Prov. Banten",
            "kode_kab_kota": "286000",
            "kabupaten_kota": "Kota Cilegon",
            "kode_kec": "286006",
            "kecamatan": "Kec. Purwakarta",
            "npsn": 70039103,
            "sekolah": "TK IT CILUKBA",
            "bentuk": "Unknown",
            "status": "Swasta",
            "sinkron_terakhir": "08 Sep 2023 10:29:56",
            "sekolah_id_enkrip": "EA51E7178F0317F1325F"
        },
        {
            "kode_prop": "280000",
            "propinsi": "Prov. Banten",
            "kode_kab_kota": "286000",
            "kabupaten_kota": "Kota Cilegon",
            "kode_kec": "286006",
            "kecamatan": "Kec. Purwakarta",
            "npsn": 70013290,
            "sekolah": "TK IT DARUSSOLEH",
            "bentuk": "Unknown",
            "status": "Swasta",
            "sinkron_terakhir": "31 Jan 2024 10:47:53",
            "sekolah_id_enkrip": "3D4E64F10786ED047F24"
        },
        {
            "kode_prop": "280000",
            "propinsi": "Prov. Banten",
            "kode_kab_kota": "286000",
            "kabupaten_kota": "Kota Cilegon",
            "kode_kec": "286006",
            "kecamatan": "Kec. Purwakarta",
            "npsn": 20614684,
            "sekolah": "TK YPWKS III",
            "bentuk": "Unknown",
            "status": "Swasta",
            "sinkron_terakhir": "26 Jan 2024 08:23:04",
            "sekolah_id_enkrip": "DE96E1805AFC9CD3A51C"
        },
        {
            "kode_prop": "280000",
            "propinsi": "Prov. Banten",
            "kode_kab_kota": "286000",
            "kabupaten_kota": "Kota Cilegon",
            "kode_kec": "286006",
            "kecamatan": "Kec. Purwakarta",
            "npsn": 69978451,
            "sekolah": "TKIT Al - I`ANAH",
            "bentuk": "Unknown",
            "status": "Swasta",
            "sinkron_terakhir": "30 Jul 2023 15:33:03",
            "sekolah_id_enkrip": "0C56E987FD4169B05E69"
        },
        {
            "kode_prop": "280000",
            "propinsi": "Prov. Banten",
            "kode_kab_kota": "286000",
            "kabupaten_kota": "Kota Cilegon",
            "kode_kec": "286006",
            "kecamatan": "Kec. Purwakarta",
            "npsn": 70035727,
            "sekolah": "TKIT AT-THOHIRIYAH",
            "bentuk": "Unknown",
            "status": "Swasta",
            "sinkron_terakhir": "27 Jan 2024 07:27:41",
            "sekolah_id_enkrip": "5EF4CB791C90BDA85C8D"
        },
        {
            "kode_prop": "280000",
            "propinsi": "Prov. Banten",
            "kode_kab_kota": "286000",
            "kabupaten_kota": "Kota Cilegon",
            "kode_kec": "286006",
            "kecamatan": "Kec. Purwakarta",
            "npsn": 60728477,
            "sekolah": "TKS ISLAM AL AZHAR 40",
            "bentuk": "Unknown",
            "status": "Swasta",
            "sinkron_terakhir": "24 Jan 2024 15:27:17",
            "sekolah_id_enkrip": "840EE6E019E06A0209EB"
        },
        {
            "kode_prop": "280000",
            "propinsi": "Prov. Banten",
            "kode_kab_kota": "286000",
            "kabupaten_kota": "Kota Cilegon",
            "kode_kec": "286006",
            "kecamatan": "Kec. Purwakarta",
            "npsn": 69798004,
            "sekolah": "KB AL MUQORROBIN",
            "bentuk": "Unknown",
            "status": "Swasta",
            "sinkron_terakhir": "01 Feb 2024 10:15:19",
            "sekolah_id_enkrip": "9505D3BA1ECD7B40CE3C"
        },
        {
            "kode_prop": "280000",
            "propinsi": "Prov. Banten",
            "kode_kab_kota": "286000",
            "kabupaten_kota": "Kota Cilegon",
            "kode_kec": "286006",
            "kecamatan": "Kec. Purwakarta",
            "npsn": 69798011,
            "sekolah": "KB AN-NUR",
            "bentuk": "Unknown",
            "status": "Swasta",
            "sinkron_terakhir": "19 Jan 2024 08:18:16",
            "sekolah_id_enkrip": "950875D89ED0947E47F9"
        },
        {
            "kode_prop": "280000",
            "propinsi": "Prov. Banten",
            "kode_kab_kota": "286000",
            "kabupaten_kota": "Kota Cilegon",
            "kode_kec": "286006",
            "kecamatan": "Kec. Purwakarta",
            "npsn": 69798008,
            "sekolah": "KB AT-THOHIRIYAH",
            "bentuk": "Unknown",
            "status": "Swasta",
            "sinkron_terakhir": "17 Jan 2024 20:16:30",
            "sekolah_id_enkrip": "ED49C8DA896D125FF2AA"
        },
        {
            "kode_prop": "280000",
            "propinsi": "Prov. Banten",
            "kode_kab_kota": "286000",
            "kabupaten_kota": "Kota Cilegon",
            "kode_kec": "286006",
            "kecamatan": "Kec. Purwakarta",
            "npsn": 69766104,
            "sekolah": "KB PAUD ABC (AMONG BOCAH CILIK)",
            "bentuk": "Unknown",
            "status": "Swasta",
            "sinkron_terakhir": "06 Feb 2024 15:56:40",
            "sekolah_id_enkrip": "DAE89567D16A8E5DCA2E"
        },
        {
            "kode_prop": "280000",
            "propinsi": "Prov. Banten",
            "kode_kab_kota": "286000",
            "kabupaten_kota": "Kota Cilegon",
            "kode_kec": "286006",
            "kecamatan": "Kec. Purwakarta",
            "npsn": 69766095,
            "sekolah": "KB PAUD AL-KAUTSAR",
            "bentuk": "Unknown",
            "status": "Swasta",
            "sinkron_terakhir": "13 Nov 2023 13:12:11",
            "sekolah_id_enkrip": "8B4533AF8D642BFE744B"
        },
        {
            "kode_prop": "280000",
            "propinsi": "Prov. Banten",
            "kode_kab_kota": "286000",
            "kabupaten_kota": "Kota Cilegon",
            "kode_kec": "286006",
            "kecamatan": "Kec. Purwakarta",
            "npsn": 69766102,
            "sekolah": "KB PAUD AL-MUHAJIRIN",
            "bentuk": "Unknown",
            "status": "Swasta",
            "sinkron_terakhir": "31 Jan 2024 12:33:44",
            "sekolah_id_enkrip": "E26526DB7D1095F46A06"
        },
        {
            "kode_prop": "280000",
            "propinsi": "Prov. Banten",
            "kode_kab_kota": "286000",
            "kabupaten_kota": "Kota Cilegon",
            "kode_kec": "286006",
            "kecamatan": "Kec. Purwakarta",
            "npsn": 69766100,
            "sekolah": "KB PAUD AS-SA ADAH",
            "bentuk": "Unknown",
            "status": "Swasta",
            "sinkron_terakhir": "29 Jan 2024 23:04:22",
            "sekolah_id_enkrip": "489F48EADF4ED7D4E44D"
        },
        {
            "kode_prop": "280000",
            "propinsi": "Prov. Banten",
            "kode_kab_kota": "286000",
            "kabupaten_kota": "Kota Cilegon",
            "kode_kec": "286006",
            "kecamatan": "Kec. Purwakarta",
            "npsn": 69766098,
            "sekolah": "KB PAUD ASH-SHOBIRIN",
            "bentuk": "Unknown",
            "status": "Swasta",
            "sinkron_terakhir": "23 Jan 2024 23:17:07",
            "sekolah_id_enkrip": "7EEAA8148FDC73A25E66"
        },
        {
            "kode_prop": "280000",
            "propinsi": "Prov. Banten",
            "kode_kab_kota": "286000",
            "kabupaten_kota": "Kota Cilegon",
            "kode_kec": "286006",
            "kecamatan": "Kec. Purwakarta",
            "npsn": 69766099,
            "sekolah": "KB PAUD PELANGI",
            "bentuk": "Unknown",
            "status": "Swasta",
            "sinkron_terakhir": "30 Jan 2024 13:52:17",
            "sekolah_id_enkrip": "D3D49F7AEED4E7B5D9D5"
        },
        {
            "kode_prop": "280000",
            "propinsi": "Prov. Banten",
            "kode_kab_kota": "286000",
            "kabupaten_kota": "Kota Cilegon",
            "kode_kec": "286006",
            "kecamatan": "Kec. Purwakarta",
            "npsn": 69766097,
            "sekolah": "KB PAUD PUTRA MAHKOTA",
            "bentuk": "Unknown",
            "status": "Swasta",
            "sinkron_terakhir": "12 Jan 2024 17:54:05",
            "sekolah_id_enkrip": "D41150D7408FF5F9139E"
        },
        {
            "kode_prop": "280000",
            "propinsi": "Prov. Banten",
            "kode_kab_kota": "286000",
            "kabupaten_kota": "Kota Cilegon",
            "kode_kec": "286006",
            "kecamatan": "Kec. Purwakarta",
            "npsn": 69766101,
            "sekolah": "KB PAUD RIFA",
            "bentuk": "Unknown",
            "status": "Swasta",
            "sinkron_terakhir": "11 Jan 2024 23:16:21",
            "sekolah_id_enkrip": "66F3B151D966AB5C72F3"
        },
        {
            "kode_prop": "280000",
            "propinsi": "Prov. Banten",
            "kode_kab_kota": "286000",
            "kabupaten_kota": "Kota Cilegon",
            "kode_kec": "286006",
            "kecamatan": "Kec. Purwakarta",
            "npsn": 69766096,
            "sekolah": "KB PAUD WIDYA",
            "bentuk": "Unknown",
            "status": "Swasta",
            "sinkron_terakhir": "09 Oct 2023 09:28:51",
            "sekolah_id_enkrip": "BC4D3ED86D9918E7C385"
        },
        {
            "kode_prop": "280000",
            "propinsi": "Prov. Banten",
            "kode_kab_kota": "286000",
            "kabupaten_kota": "Kota Cilegon",
            "kode_kec": "286006",
            "kecamatan": "Kec. Purwakarta",
            "npsn": 70042879,
            "sekolah": "KOBER AL-QUR`AN NURUL IKHLAS",
            "bentuk": "Unknown",
            "status": "Swasta",
            "sinkron_terakhir": "31 Jan 2024 10:41:09",
            "sekolah_id_enkrip": "09F579F39DE9B784A22B"
        },
        {
            "kode_prop": "280000",
            "propinsi": "Prov. Banten",
            "kode_kab_kota": "286000",
            "kabupaten_kota": "Kota Cilegon",
            "kode_kec": "286006",
            "kecamatan": "Kec. Purwakarta",
            "npsn": 70044639,
            "sekolah": "TPA DAYCARE AMANAH YPKS",
            "bentuk": "Unknown",
            "status": "Swasta",
            "sinkron_terakhir": "30 Jan 2024 15:41:31",
            "sekolah_id_enkrip": "80346921697F676BC69D"
        },
        {
            "kode_prop": "280000",
            "propinsi": "Prov. Banten",
            "kode_kab_kota": "286000",
            "kabupaten_kota": "Kota Cilegon",
            "kode_kec": "286006",
            "kecamatan": "Kec. Purwakarta",
            "npsn": 69798010,
            "sekolah": "SPS CERDAS CERIA",
            "bentuk": "Unknown",
            "status": "Swasta",
            "sinkron_terakhir": "12 Jan 2024 15:15:04",
            "sekolah_id_enkrip": "2222F3AE24A9E5184AD6"
        },
        {
            "kode_prop": "280000",
            "propinsi": "Prov. Banten",
            "kode_kab_kota": "286000",
            "kabupaten_kota": "Kota Cilegon",
            "kode_kec": "286006",
            "kecamatan": "Kec. Purwakarta",
            "npsn": 69766151,
            "sekolah": "SPS PAUD TAAM AL-AKHMAL",
            "bentuk": "Unknown",
            "status": "Swasta",
            "sinkron_terakhir": "23 Jan 2024 07:20:15",
            "sekolah_id_enkrip": "F1E5F594C4A140D0C5C9"
        },
        {
            "kode_prop": "280000",
            "propinsi": "Prov. Banten",
            "kode_kab_kota": "286000",
            "kabupaten_kota": "Kota Cilegon",
            "kode_kec": "286006",
            "kecamatan": "Kec. Purwakarta",
            "npsn": 69766153,
            "sekolah": "SPS PAUD TAAM AS-SALAM",
            "bentuk": "Unknown",
            "status": "Swasta",
            "sinkron_terakhir": "29 Jan 2024 22:13:17",
            "sekolah_id_enkrip": "BBAD7323C032F0B8E364"
        },
        {
            "kode_prop": "280000",
            "propinsi": "Prov. Banten",
            "kode_kab_kota": "286000",
            "kabupaten_kota": "Kota Cilegon",
            "kode_kec": "286006",
            "kecamatan": "Kec. Purwakarta",
            "npsn": 69766152,
            "sekolah": "SPS PAUD TAAM IQRA",
            "bentuk": "Unknown",
            "status": "Swasta",
            "sinkron_terakhir": "02 Feb 2024 08:03:32",
            "sekolah_id_enkrip": "5D694FB941200CAD921D"
        },
        {
            "kode_prop": "280000",
            "propinsi": "Prov. Banten",
            "kode_kab_kota": "286000",
            "kabupaten_kota": "Kota Cilegon",
            "kode_kec": "286006",
            "kecamatan": "Kec. Purwakarta",
            "npsn": 20606412,
            "sekolah": "SD N BLACU",
            "bentuk": "Unknown",
            "status": "Negeri",
            "sinkron_terakhir": "02 Feb 2024 11:02:23",
            "sekolah_id_enkrip": "95E9F934F7C0A42C0A42"
        },
        {
            "kode_prop": "280000",
            "propinsi": "Prov. Banten",
            "kode_kab_kota": "286000",
            "kabupaten_kota": "Kota Cilegon",
            "kode_kec": "286006",
            "kecamatan": "Kec. Purwakarta",
            "npsn": 20606212,
            "sekolah": "SD N KEBON DALEM",
            "bentuk": "Unknown",
            "status": "Negeri",
            "sinkron_terakhir": "02 Feb 2024 13:42:59",
            "sekolah_id_enkrip": "B4BD15099318C917B2A5"
        },
        {
            "kode_prop": "280000",
            "propinsi": "Prov. Banten",
            "kode_kab_kota": "286000",
            "kabupaten_kota": "Kota Cilegon",
            "kode_kec": "286006",
            "kecamatan": "Kec. Purwakarta",
            "npsn": 20606204,
            "sekolah": "SD N KENANGA",
            "bentuk": "Unknown",
            "status": "Negeri",
            "sinkron_terakhir": "02 Feb 2024 09:18:11",
            "sekolah_id_enkrip": "003768FDD7DBFC17427E"
        },
        {
            "kode_prop": "280000",
            "propinsi": "Prov. Banten",
            "kode_kab_kota": "286000",
            "kabupaten_kota": "Kota Cilegon",
            "kode_kec": "286006",
            "kecamatan": "Kec. Purwakarta",
            "npsn": 20606223,
            "sekolah": "SD N KUBANG KUTU II",
            "bentuk": "Unknown",
            "status": "Negeri",
            "sinkron_terakhir": "06 Feb 2024 09:15:05",
            "sekolah_id_enkrip": "969D7DE0B0C291361826"
        },
        {
            "kode_prop": "280000",
            "propinsi": "Prov. Banten",
            "kode_kab_kota": "286000",
            "kabupaten_kota": "Kota Cilegon",
            "kode_kec": "286006",
            "kecamatan": "Kec. Purwakarta",
            "npsn": 20606168,
            "sekolah": "SD N PABEAN",
            "bentuk": "Unknown",
            "status": "Negeri",
            "sinkron_terakhir": "02 Feb 2024 10:06:34",
            "sekolah_id_enkrip": "8948638B342E5CE457AE"
        },
        {
            "kode_prop": "280000",
            "propinsi": "Prov. Banten",
            "kode_kab_kota": "286000",
            "kabupaten_kota": "Kota Cilegon",
            "kode_kec": "286006",
            "kecamatan": "Kec. Purwakarta",
            "npsn": 20606171,
            "sekolah": "SD N PASAR BUNDER",
            "bentuk": "Unknown",
            "status": "Negeri",
            "sinkron_terakhir": "31 Jan 2024 08:04:55",
            "sekolah_id_enkrip": "9AF476B5A41D9603AD11"
        },
        {
            "kode_prop": "280000",
            "propinsi": "Prov. Banten",
            "kode_kab_kota": "286000",
            "kabupaten_kota": "Kota Cilegon",
            "kode_kec": "286006",
            "kecamatan": "Kec. Purwakarta",
            "npsn": 20606195,
            "sekolah": "SD N PURWAKARTA II",
            "bentuk": "Unknown",
            "status": "Negeri",
            "sinkron_terakhir": "19 Jan 2024 09:35:24",
            "sekolah_id_enkrip": "CAF137892DA6067515D1"
        },
        {
            "kode_prop": "280000",
            "propinsi": "Prov. Banten",
            "kode_kab_kota": "286000",
            "kabupaten_kota": "Kota Cilegon",
            "kode_kec": "286006",
            "kecamatan": "Kec. Purwakarta",
            "npsn": 20606194,
            "sekolah": "SD N RAMANUJU",
            "bentuk": "Unknown",
            "status": "Negeri",
            "sinkron_terakhir": "29 Jan 2024 12:22:33",
            "sekolah_id_enkrip": "3B3C30B697EECBDE0B42"
        },
        {
            "kode_prop": "280000",
            "propinsi": "Prov. Banten",
            "kode_kab_kota": "286000",
            "kabupaten_kota": "Kota Cilegon",
            "kode_kec": "286006",
            "kecamatan": "Kec. Purwakarta",
            "npsn": 20606186,
            "sekolah": "SD N SUMAMPIR",
            "bentuk": "Unknown",
            "status": "Negeri",
            "sinkron_terakhir": "05 Feb 2024 08:28:21",
            "sekolah_id_enkrip": "C6EF0CB302874A9228ED"
        },
        {
            "kode_prop": "280000",
            "propinsi": "Prov. Banten",
            "kode_kab_kota": "286000",
            "kabupaten_kota": "Kota Cilegon",
            "kode_kec": "286006",
            "kecamatan": "Kec. Purwakarta",
            "npsn": 20606196,
            "sekolah": "SD NEGERI PURWAKARTA I",
            "bentuk": "Unknown",
            "status": "Negeri",
            "sinkron_terakhir": "06 Feb 2024 07:58:05",
            "sekolah_id_enkrip": "784CBE75CD6C2BB4E40C"
        },
        {
            "kode_prop": "280000",
            "propinsi": "Prov. Banten",
            "kode_kab_kota": "286000",
            "kabupaten_kota": "Kota Cilegon",
            "kode_kec": "286006",
            "kecamatan": "Kec. Purwakarta",
            "npsn": 20606190,
            "sekolah": "SD NEGERI SIMPANG TIGA",
            "bentuk": "Unknown",
            "status": "Negeri",
            "sinkron_terakhir": "01 Feb 2024 16:41:26",
            "sekolah_id_enkrip": "F4EE1248DFCED9B57CF8"
        },
        {
            "kode_prop": "280000",
            "propinsi": "Prov. Banten",
            "kode_kab_kota": "286000",
            "kabupaten_kota": "Kota Cilegon",
            "kode_kec": "286006",
            "kecamatan": "Kec. Purwakarta",
            "npsn": 20606172,
            "sekolah": "SD. NEGERI PECINAN",
            "bentuk": "Unknown",
            "status": "Negeri",
            "sinkron_terakhir": "23 Jan 2024 11:17:24",
            "sekolah_id_enkrip": "CCC3B98340584C26A017"
        },
        {
            "kode_prop": "280000",
            "propinsi": "Prov. Banten",
            "kode_kab_kota": "286000",
            "kabupaten_kota": "Kota Cilegon",
            "kode_kec": "286006",
            "kecamatan": "Kec. Purwakarta",
            "npsn": 20606230,
            "sekolah": "SDN KOTA BUMI",
            "bentuk": "Unknown",
            "status": "Negeri",
            "sinkron_terakhir": "02 Feb 2024 07:39:45",
            "sekolah_id_enkrip": "E6B7B27F87BF0FEE1457"
        },
        {
            "kode_prop": "280000",
            "propinsi": "Prov. Banten",
            "kode_kab_kota": "286000",
            "kabupaten_kota": "Kota Cilegon",
            "kode_kec": "286006",
            "kecamatan": "Kec. Purwakarta",
            "npsn": 20606226,
            "sekolah": "SDN KUBANG KALAK",
            "bentuk": "Unknown",
            "status": "Negeri",
            "sinkron_terakhir": "06 Feb 2024 10:30:38",
            "sekolah_id_enkrip": "2481B3D8C8C80004C991"
        },
        {
            "kode_prop": "280000",
            "propinsi": "Prov. Banten",
            "kode_kab_kota": "286000",
            "kabupaten_kota": "Kota Cilegon",
            "kode_kec": "286006",
            "kecamatan": "Kec. Purwakarta",
            "npsn": 20606224,
            "sekolah": "SDN KUBANGKUTU I",
            "bentuk": "Unknown",
            "status": "Negeri",
            "sinkron_terakhir": "18 Jan 2024 11:26:46",
            "sekolah_id_enkrip": "F41CBF33757D31E9A9A4"
        },
        {
            "kode_prop": "280000",
            "propinsi": "Prov. Banten",
            "kode_kab_kota": "286000",
            "kabupaten_kota": "Kota Cilegon",
            "kode_kec": "286006",
            "kecamatan": "Kec. Purwakarta",
            "npsn": 20606197,
            "sekolah": "SDN PURWAKARTA",
            "bentuk": "Unknown",
            "status": "Negeri",
            "sinkron_terakhir": "02 Feb 2024 09:10:05",
            "sekolah_id_enkrip": "6ED781C780902429382A"
        },
        {
            "kode_prop": "280000",
            "propinsi": "Prov. Banten",
            "kode_kab_kota": "286000",
            "kabupaten_kota": "Kota Cilegon",
            "kode_kec": "286006",
            "kecamatan": "Kec. Purwakarta",
            "npsn": 20606330,
            "sekolah": "SD AZ-ZAHRA",
            "bentuk": "Unknown",
            "status": "Swasta",
            "sinkron_terakhir": "15 Jan 2024 11:09:51",
            "sekolah_id_enkrip": "74B1351C25BF101BA3AC"
        },
        {
            "kode_prop": "280000",
            "propinsi": "Prov. Banten",
            "kode_kab_kota": "286000",
            "kabupaten_kota": "Kota Cilegon",
            "kode_kec": "286006",
            "kecamatan": "Kec. Purwakarta",
            "npsn": 20623091,
            "sekolah": "SD ISLAM AL-AZHAR 40 YPKS",
            "bentuk": "Unknown",
            "status": "Swasta",
            "sinkron_terakhir": "01 Feb 2024 11:41:18",
            "sekolah_id_enkrip": "3995B3545CD517A82820"
        },
        {
            "kode_prop": "280000",
            "propinsi": "Prov. Banten",
            "kode_kab_kota": "286000",
            "kabupaten_kota": "Kota Cilegon",
            "kode_kec": "286006",
            "kecamatan": "Kec. Purwakarta",
            "npsn": 70025603,
            "sekolah": "SD IT Tunas Cendekia Cilegon",
            "bentuk": "Unknown",
            "status": "Swasta",
            "sinkron_terakhir": "24 Jan 2024 15:10:23",
            "sekolah_id_enkrip": "5DDF13FC67789745A24B"
        },
        {
            "kode_prop": "280000",
            "propinsi": "Prov. Banten",
            "kode_kab_kota": "286000",
            "kabupaten_kota": "Kota Cilegon",
            "kode_kec": "286006",
            "kecamatan": "Kec. Purwakarta",
            "npsn": 20606422,
            "sekolah": "SD S YPWKS II",
            "bentuk": "Unknown",
            "status": "Swasta",
            "sinkron_terakhir": "30 Jan 2024 09:20:32",
            "sekolah_id_enkrip": "4EE9D8CDA0565FDC5A97"
        },
        {
            "kode_prop": "280000",
            "propinsi": "Prov. Banten",
            "kode_kab_kota": "286000",
            "kabupaten_kota": "Kota Cilegon",
            "kode_kec": "286006",
            "kecamatan": "Kec. Purwakarta",
            "npsn": 20606421,
            "sekolah": "SD SN YPWKS IV",
            "bentuk": "Unknown",
            "status": "Swasta",
            "sinkron_terakhir": "05 Feb 2024 09:58:59",
            "sekolah_id_enkrip": "63F9EA5E91B4164BDDAA"
        },
        {
            "kode_prop": "280000",
            "propinsi": "Prov. Banten",
            "kode_kab_kota": "286000",
            "kabupaten_kota": "Kota Cilegon",
            "kode_kec": "286006",
            "kecamatan": "Kec. Purwakarta",
            "npsn": 20614891,
            "sekolah": "SDIT AL - MUQORROBIN",
            "bentuk": "Unknown",
            "status": "Swasta",
            "sinkron_terakhir": "19 Jan 2024 16:00:46",
            "sekolah_id_enkrip": "E0DD73BAD621249E606F"
        },
        {
            "kode_prop": "280000",
            "propinsi": "Prov. Banten",
            "kode_kab_kota": "286000",
            "kabupaten_kota": "Kota Cilegon",
            "kode_kec": "286006",
            "kecamatan": "Kec. Purwakarta",
            "npsn": 70010890,
            "sekolah": "SMP NEGERI 12 CILEGON",
            "bentuk": "Unknown",
            "status": "Negeri",
            "sinkron_terakhir": "01 Feb 2024 16:21:23",
            "sekolah_id_enkrip": "8BF97DDC8B9186512FDC"
        },
        {
            "kode_prop": "280000",
            "propinsi": "Prov. Banten",
            "kode_kab_kota": "286000",
            "kabupaten_kota": "Kota Cilegon",
            "kode_kec": "286006",
            "kecamatan": "Kec. Purwakarta",
            "npsn": 20613571,
            "sekolah": "SMP ISLAM AL AZHAR 27 CILEGON",
            "bentuk": "Unknown",
            "status": "Swasta",
            "sinkron_terakhir": "05 Feb 2024 16:10:09",
            "sekolah_id_enkrip": "3C63AA39D79B59E76626"
        },
        {
            "kode_prop": "280000",
            "propinsi": "Prov. Banten",
            "kode_kab_kota": "286000",
            "kabupaten_kota": "Kota Cilegon",
            "kode_kec": "286006",
            "kecamatan": "Kec. Purwakarta",
            "npsn": 70013451,
            "sekolah": "SMP IT AL-MUQORROBIN",
            "bentuk": "Unknown",
            "status": "Swasta",
            "sinkron_terakhir": "26 Jan 2024 08:47:25",
            "sekolah_id_enkrip": "090050B819F82AA1B0E7"
        },
        {
            "kode_prop": "280000",
            "propinsi": "Prov. Banten",
            "kode_kab_kota": "286000",
            "kabupaten_kota": "Kota Cilegon",
            "kode_kec": "286006",
            "kecamatan": "Kec. Purwakarta",
            "npsn": 20606252,
            "sekolah": "SMP MADINATUL HADID",
            "bentuk": "Unknown",
            "status": "Swasta",
            "sinkron_terakhir": "27 Dec 2023 20:53:13",
            "sekolah_id_enkrip": "F98E33BF9E846025DB61"
        },
        {
            "kode_prop": "280000",
            "propinsi": "Prov. Banten",
            "kode_kab_kota": "286000",
            "kabupaten_kota": "Kota Cilegon",
            "kode_kec": "286006",
            "kecamatan": "Kec. Purwakarta",
            "npsn": 20606265,
            "sekolah": "SMP TUNAS BANGSA",
            "bentuk": "Unknown",
            "status": "Swasta",
            "sinkron_terakhir": "23 Jan 2024 08:46:07",
            "sekolah_id_enkrip": "625C858DCB0C48E1D254"
        },
        {
            "kode_prop": "280000",
            "propinsi": "Prov. Banten",
            "kode_kab_kota": "286000",
            "kabupaten_kota": "Kota Cilegon",
            "kode_kec": "286006",
            "kecamatan": "Kec. Purwakarta",
            "npsn": 20606263,
            "sekolah": "SMP YPWKS",
            "bentuk": "Unknown",
            "status": "Swasta",
            "sinkron_terakhir": "05 Feb 2024 10:40:11",
            "sekolah_id_enkrip": "CD40D4023C2CB039F452"
        },
        {
            "kode_prop": "280000",
            "propinsi": "Prov. Banten",
            "kode_kab_kota": "286000",
            "kabupaten_kota": "Kota Cilegon",
            "kode_kec": "286006",
            "kecamatan": "Kec. Purwakarta",
            "npsn": 20606271,
            "sekolah": "SMAN 2 KRAKATAU STEEL CILEGON",
            "bentuk": "SMA",
            "status": "Negeri",
            "sinkron_terakhir": "06 Feb 2024 17:32:33",
            "sekolah_id_enkrip": "D7411665FED090AD5B46"
        },
        {
            "kode_prop": "280000",
            "propinsi": "Prov. Banten",
            "kode_kab_kota": "286000",
            "kabupaten_kota": "Kota Cilegon",
            "kode_kec": "286006",
            "kecamatan": "Kec. Purwakarta",
            "npsn": 20606291,
            "sekolah": "SMAS AL MA ARIF",
            "bentuk": "SMA",
            "status": "Swasta",
            "sinkron_terakhir": "03 Feb 2024 23:11:08",
            "sekolah_id_enkrip": "29118304F654C1E7970B"
        },
        {
            "kode_prop": "280000",
            "propinsi": "Prov. Banten",
            "kode_kab_kota": "286000",
            "kabupaten_kota": "Kota Cilegon",
            "kode_kec": "286006",
            "kecamatan": "Kec. Purwakarta",
            "npsn": 60724663,
            "sekolah": "SMAS ISLAM AL AZHAR 6",
            "bentuk": "SMA",
            "status": "Swasta",
            "sinkron_terakhir": "05 Feb 2024 10:03:43",
            "sekolah_id_enkrip": "398B1805D904457979C3"
        },
        {
            "kode_prop": "280000",
            "propinsi": "Prov. Banten",
            "kode_kab_kota": "286000",
            "kabupaten_kota": "Kota Cilegon",
            "kode_kec": "286006",
            "kecamatan": "Kec. Purwakarta",
            "npsn": 69772965,
            "sekolah": "SMKS INFORMATIKA SUKMA MANDIRI",
            "bentuk": "SMK",
            "status": "Swasta",
            "sinkron_terakhir": "31 Jan 2024 10:31:58",
            "sekolah_id_enkrip": "A2BC399A2777F67169E2"
        },
        {
            "kode_prop": "280000",
            "propinsi": "Prov. Banten",
            "kode_kab_kota": "286000",
            "kabupaten_kota": "Kota Cilegon",
            "kode_kec": "286006",
            "kecamatan": "Kec. Purwakarta",
            "npsn": 69772962,
            "sekolah": "SMKS MADINATUL HADID",
            "bentuk": "SMK",
            "status": "Swasta",
            "sinkron_terakhir": "05 Feb 2024 14:44:09",
            "sekolah_id_enkrip": "033EC3E2B3EEDA0980E3"
        },
        {
            "kode_prop": "280000",
            "propinsi": "Prov. Banten",
            "kode_kab_kota": "286000",
            "kabupaten_kota": "Kota Cilegon",
            "kode_kec": "286006",
            "kecamatan": "Kec. Purwakarta",
            "npsn": 20606244,
            "sekolah": "SMKS YPWKS CILEGON",
            "bentuk": "SMK",
            "status": "Swasta",
            "sinkron_terakhir": "05 Feb 2024 13:27:17",
            "sekolah_id_enkrip": "F8B49F055D8B1595B86D"
        },
        {
            "kode_prop": "280000",
            "propinsi": "Prov. Banten",
            "kode_kab_kota": "286000",
            "kabupaten_kota": "Kota Cilegon",
            "kode_kec": "286006",
            "kecamatan": "Kec. Purwakarta",
            "npsn": "P9908669",
            "sekolah": "PKBM AL-INSYIROH",
            "bentuk": "PKBM",
            "status": "Swasta",
            "sinkron_terakhir": "31 Aug 2023 17:08:22",
            "sekolah_id_enkrip": "BC2439A06F0AD8C49565"
        },
        {
            "kode_prop": "280000",
            "propinsi": "Prov. Banten",
            "kode_kab_kota": "286000",
            "kabupaten_kota": "Kota Cilegon",
            "kode_kec": "286006",
            "kecamatan": "Kec. Purwakarta",
            "npsn": "P9948465",
            "sekolah": "PKBM WIDYA BINA KARYA",
            "bentuk": "PKBM",
            "status": "Swasta",
            "sinkron_terakhir": "02 Feb 2024 20:52:15",
            "sekolah_id_enkrip": "1E8D63F5DBF4B62F3989"
        }
    ]
}